Workbook

Sheet Panduan
A1: Digital Ads Ultimate Skill 2026: Workbook Latihan
A2: Praktik end-to-end Google, Meta, TikTok, LinkedIn, dan marketplace. Semua data FIKTIF (brand contoh Nusa Apparel). Repo: github.com/shafry00/digital-ads-ultimate-skill-2026
A4: CARA PAKAI (5 langkah)
A5: 1. Isi Asumsi | B5: Buka sheet Asumsi. Ganti sel kuning (harga, HPP, bantalan profit, target POAS, ekonomi B2B) dengan angka bisnismu.
A6: 2. Tempel data | B6: Di tiap sheet platform, ganti sel BIRU dengan ekspor akunmu. Baris contoh sudah ada, timpa saja. Ada ruang 30 baris per sheet. Sel hitam adalah rumus, jangan ditimpa.
A7: 3. Baca verdict | B7: Kolom Verdict menilai tiap baris: SCALE, HOLD, FIX, CUT, LOW DATA, atau diagnosis khusus (FATIGUE, FIX LANDING, FIX HOOK, FIX CTA/BODY, CEK MER).
A8: 4. Lihat Dashboard | B8: Ringkasan lintas platform: biaya, ROAS, POAS, MER, baris paling bermasalah, grafik.
A9: 5. Latihan dan agent | B9: Kerjakan sheet Latihan. Lalu lampirkan file ini ke agent dan salin prompt di kolom F (skill digital-ads-ultimate sudah terpasang).
A11: KODE WARNA
A12: Biru | B12: Input atau data yang kamu isi.
A13: Hitam | B13: Rumus. Jangan ditimpa.
A14: Hijau | B14: Tautan dari sheet lain.
A15: Latar kuning | B15: Asumsi kunci yang wajib kamu ganti.
A17: PETA SHEET
A18: Asumsi | B18: Ekonomi per pesanan, target, ambang penilaian, ekonomi B2B, target marketplace.
A19: Google Ads | B19: 6 campaign (Brand, Non-Brand, Kompetitor, PMax, Demand Gen, YouTube) + tabel search terms untuk latihan negative keyword.
A20: Meta Ads | B20: 7 iklan: ada yang fatigue, hook bagus tapi CVR rendah, dan data kurang.
A21: TikTok Ads | B21: 7 kreatif: pemenang Spark, hook lemah, CTA lemah, fatigue.
A22: LinkedIn Ads | B22: 6 campaign B2B sampai SQL dan deal Won: lead murah tapi tidak jadi SQL.
A23: Marketplace | B23: 10 baris Shopee, Tokopedia, TikTok Shop: ROAS tinggi tapi POAS rendah, plus TACoS per platform.
A24: Mingguan | B24: 8 minggu: MER, break-even MER, klaim platform vs omzet nyata, CAC, laba setelah iklan.
A25: Dashboard | B25: Ringkasan dan grafik.
A26: Latihan | B26: 13 tugas dengan kunci jawaban berupa rumus dan prompt siap salin.
A28: METRIK
A29: ROAS | B29: Omzet iklan / biaya iklan. Tidak memperhitungkan HPP, fee, voucher, retur.
A30: POAS | B30: Kontribusi sebelum iklan dari omzet iklan / biaya iklan. Impas di 1,0. POAS = ROAS x margin kontribusi.
A31: MER | B31: Omzet bisnis total / total biaya marketing semua channel.
A32: TACoS | B32: Biaya iklan / omzet total toko (iklan + organik). Untuk marketplace.
A33: Break-even ROAS | B33: 1 / margin kontribusi. Batas bawah ROAS sebelum iklan rugi.
A35: CATATAN PENTING
A36: Data fiktif | B36: Semua angka dan nama produk dibuat untuk latihan, bukan benchmark industri.
A37: Ambang heuristik | B37: Batas hook rate, CTR, CVR, frekuensi, POAS di sheet Asumsi adalah titik awal. Kalibrasi dengan data akunmu sendiri.
A38: Fee marketplace | B38: Komisi dan biaya tetap berubah. Isi dari halaman biaya terbaru di Seller Center.
A39: Verdict bukan perintah | B39: Verdict adalah sinyal awal. Cek lag konversi, volume data, tracking, dan peran campaign sebelum memotong budget.
A40: English | B40: Quick start: replace blue cells with your own exports, set the yellow assumptions, read the Verdict columns and Dashboard, then attach this file to your agent with the prompts in the Latihan sheet (column F, translate or adapt as needed).

Sheet Asumsi
A1: Asumsi dan Ambang Penilaian
A2: Sel biru = input, kuning = asumsi kunci yang WAJIB kamu ganti dengan angka bisnismu. Semua sheet platform membaca dari sini.
A3: EKONOMI PENJUALAN WEBSITE (DTC): dipakai Google, Meta, TikTok
A4: Harga jual rata-rata per pesanan (Rp) | B4: 150000 | C4: Isi harga realisasi, bukan harga coret. Contoh fiktif.
A5: HPP per pesanan (Rp) | B5: 62000 | C5: Harga pokok sampai gudang (produk + inbound + QC).
A6: Biaya payment (% harga) | B6: 0.02 | C6: Gateway, VA, e-wallet.
A7: Subsidi ongkir per pesanan (Rp) | B7: 8000 | C7: Ongkir yang kamu tanggung.
A8: Packaging per pesanan (Rp) | B8: 2000
A9: Cadangan retur/cancel (% harga) | B9: 0.03 | C9: Ambil dari 90 hari terakhir.
A10: Kontribusi per pesanan (Rp) | B10: =B4*(1-B6-B9)-B5-B7-B8 -> 70500 | C10: Rumus. Harga dikurangi biaya variabel.
A11: Margin kontribusi (%) | B11: =B10/B4 -> 0.47 | C11: Rumus.
A12: Break-even ROAS | B12: =1/B11 -> 2.1276596 | C12: Rumus. Di bawah ini iklan rugi di level kontribusi.
A13: Break-even CPA (Rp) | B13: =B10 -> 70500 | C13: Rumus. Pesanan pertama.
A14: Bantalan profit (% dari break-even) | B14: 0.3 | C14: Sisakan untuk overhead dan risiko.
A15: Target CPA (Rp) | B15: =B13*(1-B14) -> 49350 | C15: Rumus.
A16: Target POAS | B16: 1.3 | C16: Heuristik 1,2 sampai 1,5. POAS 1,0 = impas.
A17: Target ROAS | B17: =B12*B16 -> 2.7659574 | C17: Rumus: break-even ROAS x target POAS.
A19: AMBANG PENILAIAN (heuristik, ubah sesuai akunmu)
A20: Minimum konversi/pesanan agar baris dinilai | B20: 5 | C20: Di bawah ini = LOW DATA.
A21: Batas frekuensi Meta prospecting (FATIGUE) | B21: 3 | C21: Heuristik.
A22: Hook rate minimum | B22: 0.25 | C22: Meta: tayang 3 detik / impresi. TikTok: tayang 2 detik / impresi. Heuristik, kalibrasi dengan akunmu.
A23: CTR minimum (link) | B23: 0.008 | C23: Heuristik.
A24: CVR minimum klik ke beli (Meta) | B24: 0.015 | C24: Heuristik.
A25: Rasio CTR sekarang / sebelumnya di bawah ini = FATIGUE | B25: 0.7 | C25: TikTok.
A26: Batas POAS untuk HOLD | B26: 1 | C26: Di atas ini tapi di bawah target = HOLD.
A27: Batas POAS untuk FIX | B27: 0.7 | C27: Di bawah ini = CUT.
A29: EKONOMI B2B (LinkedIn)
A30: Nilai kontrak rata-rata (Rp) | B30: 45000000 | C30: Contoh fiktif: seragam korporat.
A31: Margin kontribusi B2B (%) | B31: 0.3
A32: Kontribusi per deal (Rp) | B32: =B30*B31 -> 13500000 | C32: Rumus.
A33: Rasio SQL ke Won (%) | B33: 0.2 | C33: Ambil dari CRM.
A34: Nilai per SQL (Rp) | B34: =B32*B33 -> 2700000 | C34: Rumus.
A35: Bantalan profit B2B (%) | B35: 0.4
A36: Maksimal biaya per SQL (Rp) | B36: =B34*(1-B35) -> 1620000 | C36: Rumus. Pembanding verdict LinkedIn.
A37: Minimum SQL agar baris dinilai | B37: 3
A39: MARKETPLACE (Shopee, Tokopedia, TikTok Shop)
A40: Target POAS marketplace | B40: 1.3 | C40: Boleh beda dari DTC.
A41: Minimum pesanan agar baris dinilai | B41: 5

Sheet Google Ads
A1: Google Ads: data campaign
A2: September 2026, data FIKTIF untuk latihan. Ganti sel biru dengan ekspor akunmu. Brand contoh: Nusa Apparel (fashion).
A5: TOTAL / RASIO | D5: =SUM(D7:D36) -> 4478000 | E5: =SUM(E7:E36) -> 55700 | F5: =SUM(F7:F36) -> 114150000 | G5: =SUM(G7:G36) -> 1583 | H5: =SUM(H7:H36) -> 237450000 | J5: =IFERROR(E5/D5,"") -> 0.012438589 | K5: =IFERROR(F5/E5,"") -> 2049.3716 | L5: =IFERROR(G5/E5,"") -> 0.028420108 | M5: =IFERROR(F5/G5,"") -> 72109.918 | N5: =IFERROR(H5/F5,"") -> 2.0801577 | P5: =IFERROR(N5*Asumsi!$B$11,"") -> 0.97767411
A6: Campaign | B6: Tipe | C6: Peran (Capture/Create/Defend) | D6: Impresi | E6: Klik | F6: Biaya (Rp) | G6: Konversi | H6: Nilai konversi (Rp) | I6: Porsi konversi brand (opsional, PMax) | J6: CTR | K6: CPC (Rp) | L6: CVR | M6: CPA (Rp) | N6: ROAS | O6: ROAS tanpa brand | P6: POAS | Q6: Verdict | R6: Catatan
A7: Search | Brand | B7: Search | C7: Defend | D7: 48000 | E7: 6200 | F7: 9300000 | G7: 410 | H7: 61500000 | J7: =IF(F7="","",IFERROR(E7/D7,"")) -> 0.12916667 | K7: =IF(F7="","",IFERROR(F7/E7,"")) -> 1500 | L7: =IF(F7="","",IFERROR(G7/E7,"")) -> 0.066129032 | M7: =IF(F7="","",IFERROR(F7/G7,"")) -> 22682.927 | N7: =IF(F7="","",IFERROR(H7/F7,"")) -> 6.6129032 | O7: =IF(F7="","",IF(I7="","",N7*(1-I7))) | P7: =IF(F7="","",IFERROR(N7*Asumsi!$B$11,"")) -> 3.1080645 | Q7: =IF(F7="","",IF(G7<Asumsi!$B$20,"LOW DATA",IF(P7>=Asumsi!$B$16,"SCALE",IF(P7>=Asumsi!$B$26,"HOLD",IF(C7="Create","CEK MER",IF(P7>=Asumsi!$B$27,"FIX","CUT")))))) -> SCALE | R7: ROAS tinggi karena orang sudah cari brand. Jangan jadikan bukti iklan 'menciptakan' demand.
A8: Search | Non-Brand Produk | B8: Search | C8: Capture | D8: 310000 | E8: 9300 | F8: 41850000 | G8: 470 | H8: 70500000 | J8: =IF(F8="","",IFERROR(E8/D8,"")) -> 0.03 | K8: =IF(F8="","",IFERROR(F8/E8,"")) -> 4500 | L8: =IF(F8="","",IFERROR(G8/E8,"")) -> 0.050537634 | M8: =IF(F8="","",IFERROR(F8/G8,"")) -> 89042.553 | N8: =IF(F8="","",IFERROR(H8/F8,"")) -> 1.6845878 | O8: =IF(F8="","",IF(I8="","",N8*(1-I8))) | P8: =IF(F8="","",IFERROR(N8*Asumsi!$B$11,"")) -> 0.79175627 | Q8: =IF(F8="","",IF(G8<Asumsi!$B$20,"LOW DATA",IF(P8>=Asumsi!$B$16,"SCALE",IF(P8>=Asumsi!$B$26,"HOLD",IF(C8="Create","CEK MER",IF(P8>=Asumsi!$B$27,"FIX","CUT")))))) -> FIX | R8: Terbesar di biaya. Cek tabel search terms di bawah untuk pemborosan.
A9: Search | Kompetitor | B9: Search | C9: Capture | D9: 90000 | E9: 1800 | F9: 8100000 | G9: 28 | H9: 4200000 | J9: =IF(F9="","",IFERROR(E9/D9,"")) -> 0.02 | K9: =IF(F9="","",IFERROR(F9/E9,"")) -> 4500 | L9: =IF(F9="","",IFERROR(G9/E9,"")) -> 0.015555556 | M9: =IF(F9="","",IFERROR(F9/G9,"")) -> 289285.71 | N9: =IF(F9="","",IFERROR(H9/F9,"")) -> 0.51851852 | O9: =IF(F9="","",IF(I9="","",N9*(1-I9))) | P9: =IF(F9="","",IFERROR(N9*Asumsi!$B$11,"")) -> 0.2437037 | Q9: =IF(F9="","",IF(G9<Asumsi!$B$20,"LOW DATA",IF(P9>=Asumsi!$B$16,"SCALE",IF(P9>=Asumsi!$B$26,"HOLD",IF(C9="Create","CEK MER",IF(P9>=Asumsi!$B$27,"FIX","CUT")))))) -> CUT | R9: Klik mahal, jarang beli.
A10: PMax | Feed Produk | B10: Performance Max | C10: Capture | D10: 1250000 | E10: 21000 | F10: 36000000 | G10: 520 | H10: 78000000 | I10: 0.38 | J10: =IF(F10="","",IFERROR(E10/D10,"")) -> 0.0168 | K10: =IF(F10="","",IFERROR(F10/E10,"")) -> 1714.2857 | L10: =IF(F10="","",IFERROR(G10/E10,"")) -> 0.024761905 | M10: =IF(F10="","",IFERROR(F10/G10,"")) -> 69230.769 | N10: =IF(F10="","",IFERROR(H10/F10,"")) -> 2.1666667 | O10: =IF(F10="","",IF(I10="","",N10*(1-I10))) -> 1.3433333 | P10: =IF(F10="","",IFERROR(N10*Asumsi!$B$11,"")) -> 1.0183333 | Q10: =IF(F10="","",IF(G10<Asumsi!$B$20,"LOW DATA",IF(P10>=Asumsi!$B$16,"SCALE",IF(P10>=Asumsi!$B$26,"HOLD",IF(C10="Create","CEK MER",IF(P10>=Asumsi!$B$27,"FIX","CUT")))))) -> HOLD | R10: Cek porsi brand: ROAS tanpa brand lebih jujur.
A11: Demand Gen | Prospecting | B11: Demand Gen | C11: Create | D11: 2400000 | E11: 14400 | F11: 14400000 | G11: 60 | H11: 9000000 | J11: =IF(F11="","",IFERROR(E11/D11,"")) -> 0.006 | K11: =IF(F11="","",IFERROR(F11/E11,"")) -> 1000 | L11: =IF(F11="","",IFERROR(G11/E11,"")) -> 0.0041666667 | M11: =IF(F11="","",IFERROR(F11/G11,"")) -> 240000 | N11: =IF(F11="","",IFERROR(H11/F11,"")) -> 0.625 | O11: =IF(F11="","",IF(I11="","",N11*(1-I11))) | P11: =IF(F11="","",IFERROR(N11*Asumsi!$B$11,"")) -> 0.29375 | Q11: =IF(F11="","",IF(G11<Asumsi!$B$20,"LOW DATA",IF(P11>=Asumsi!$B$16,"SCALE",IF(P11>=Asumsi!$B$26,"HOLD",IF(C11="Create","CEK MER",IF(P11>=Asumsi!$B$27,"FIX","CUT")))))) -> CEK MER | R11: Peran Create. Last-click menipu, nilai lewat MER dan brand search.
A12: YouTube | Retargeting Viewer | B12: YouTube | C12: Capture | D12: 380000 | E12: 3000 | F12: 4500000 | G12: 95 | H12: 14250000 | J12: =IF(F12="","",IFERROR(E12/D12,"")) -> 0.0078947368 | K12: =IF(F12="","",IFERROR(F12/E12,"")) -> 1500 | L12: =IF(F12="","",IFERROR(G12/E12,"")) -> 0.031666667 | M12: =IF(F12="","",IFERROR(F12/G12,"")) -> 47368.421 | N12: =IF(F12="","",IFERROR(H12/F12,"")) -> 3.1666667 | O12: =IF(F12="","",IF(I12="","",N12*(1-I12))) | P12: =IF(F12="","",IFERROR(N12*Asumsi!$B$11,"")) -> 1.4883333 | Q12: =IF(F12="","",IF(G12<Asumsi!$B$20,"LOW DATA",IF(P12>=Asumsi!$B$16,"SCALE",IF(P12>=Asumsi!$B$26,"HOLD",IF(C12="Create","CEK MER",IF(P12>=Asumsi!$B$27,"FIX","CUT")))))) -> SCALE | R12: Kecil tapi efisien.
J13: =IF(F13="","",IFERROR(E13/D13,"")) | K13: =IF(F13="","",IFERROR(F13/E13,"")) | L13: =IF(F13="","",IFERROR(G13/E13,"")) | M13: =IF(F13="","",IFERROR(F13/G13,"")) | N13: =IF(F13="","",IFERROR(H13/F13,"")) | O13: =IF(F13="","",IF(I13="","",N13*(1-I13))) | P13: =IF(F13="","",IFERROR(N13*Asumsi!$B$11,"")) | Q13: =IF(F13="","",IF(G13<Asumsi!$B$20,"LOW DATA",IF(P13>=Asumsi!$B$16,"SCALE",IF(P13>=Asumsi!$B$26,"HOLD",IF(C13="Create","CEK MER",IF(P13>=Asumsi!$B$27,"FIX","CUT"))))))
J14: =IF(F14="","",IFERROR(E14/D14,"")) | K14: =IF(F14="","",IFERROR(F14/E14,"")) | L14: =IF(F14="","",IFERROR(G14/E14,"")) | M14: =IF(F14="","",IFERROR(F14/G14,"")) | N14: =IF(F14="","",IFERROR(H14/F14,"")) | O14: =IF(F14="","",IF(I14="","",N14*(1-I14))) | P14: =IF(F14="","",IFERROR(N14*Asumsi!$B$11,"")) | Q14: =IF(F14="","",IF(G14<Asumsi!$B$20,"LOW DATA",IF(P14>=Asumsi!$B$16,"SCALE",IF(P14>=Asumsi!$B$26,"HOLD",IF(C14="Create","CEK MER",IF(P14>=Asumsi!$B$27,"FIX","CUT"))))))
J15: =IF(F15="","",IFERROR(E15/D15,"")) | K15: =IF(F15="","",IFERROR(F15/E15,"")) | L15: =IF(F15="","",IFERROR(G15/E15,"")) | M15: =IF(F15="","",IFERROR(F15/G15,"")) | N15: =IF(F15="","",IFERROR(H15/F15,"")) | O15: =IF(F15="","",IF(I15="","",N15*(1-I15))) | P15: =IF(F15="","",IFERROR(N15*Asumsi!$B$11,"")) | Q15: =IF(F15="","",IF(G15<Asumsi!$B$20,"LOW DATA",IF(P15>=Asumsi!$B$16,"SCALE",IF(P15>=Asumsi!$B$26,"HOLD",IF(C15="Create","CEK MER",IF(P15>=Asumsi!$B$27,"FIX","CUT"))))))
J16: =IF(F16="","",IFERROR(E16/D16,"")) | K16: =IF(F16="","",IFERROR(F16/E16,"")) | L16: =IF(F16="","",IFERROR(G16/E16,"")) | M16: =IF(F16="","",IFERROR(F16/G16,"")) | N16: =IF(F16="","",IFERROR(H16/F16,"")) | O16: =IF(F16="","",IF(I16="","",N16*(1-I16))) | P16: =IF(F16="","",IFERROR(N16*Asumsi!$B$11,"")) | Q16: =IF(F16="","",IF(G16<Asumsi!$B$20,"LOW DATA",IF(P16>=Asumsi!$B$16,"SCALE",IF(P16>=Asumsi!$B$26,"HOLD",IF(C16="Create","CEK MER",IF(P16>=Asumsi!$B$27,"FIX","CUT"))))))
J17: =IF(F17="","",IFERROR(E17/D17,"")) | K17: =IF(F17="","",IFERROR(F17/E17,"")) | L17: =IF(F17="","",IFERROR(G17/E17,"")) | M17: =IF(F17="","",IFERROR(F17/G17,"")) | N17: =IF(F17="","",IFERROR(H17/F17,"")) | O17: =IF(F17="","",IF(I17="","",N17*(1-I17))) | P17: =IF(F17="","",IFERROR(N17*Asumsi!$B$11,"")) | Q17: =IF(F17="","",IF(G17<Asumsi!$B$20,"LOW DATA",IF(P17>=Asumsi!$B$16,"SCALE",IF(P17>=Asumsi!$B$26,"HOLD",IF(C17="Create","CEK MER",IF(P17>=Asumsi!$B$27,"FIX","CUT"))))))
J18: =IF(F18="","",IFERROR(E18/D18,"")) | K18: =IF(F18="","",IFERROR(F18/E18,"")) | L18: =IF(F18="","",IFERROR(G18/E18,"")) | M18: =IF(F18="","",IFERROR(F18/G18,"")) | N18: =IF(F18="","",IFERROR(H18/F18,"")) | O18: =IF(F18="","",IF(I18="","",N18*(1-I18))) | P18: =IF(F18="","",IFERROR(N18*Asumsi!$B$11,"")) | Q18: =IF(F18="","",IF(G18<Asumsi!$B$20,"LOW DATA",IF(P18>=Asumsi!$B$16,"SCALE",IF(P18>=Asumsi!$B$26,"HOLD",IF(C18="Create","CEK MER",IF(P18>=Asumsi!$B$27,"FIX","CUT"))))))
J19: =IF(F19="","",IFERROR(E19/D19,"")) | K19: =IF(F19="","",IFERROR(F19/E19,"")) | L19: =IF(F19="","",IFERROR(G19/E19,"")) | M19: =IF(F19="","",IFERROR(F19/G19,"")) | N19: =IF(F19="","",IFERROR(H19/F19,"")) | O19: =IF(F19="","",IF(I19="","",N19*(1-I19))) | P19: =IF(F19="","",IFERROR(N19*Asumsi!$B$11,"")) | Q19: =IF(F19="","",IF(G19<Asumsi!$B$20,"LOW DATA",IF(P19>=Asumsi!$B$16,"SCALE",IF(P19>=Asumsi!$B$26,"HOLD",IF(C19="Create","CEK MER",IF(P19>=Asumsi!$B$27,"FIX","CUT"))))))
J20: =IF(F20="","",IFERROR(E20/D20,"")) | K20: =IF(F20="","",IFERROR(F20/E20,"")) | L20: =IF(F20="","",IFERROR(G20/E20,"")) | M20: =IF(F20="","",IFERROR(F20/G20,"")) | N20: =IF(F20="","",IFERROR(H20/F20,"")) | O20: =IF(F20="","",IF(I20="","",N20*(1-I20))) | P20: =IF(F20="","",IFERROR(N20*Asumsi!$B$11,"")) | Q20: =IF(F20="","",IF(G20<Asumsi!$B$20,"LOW DATA",IF(P20>=Asumsi!$B$16,"SCALE",IF(P20>=Asumsi!$B$26,"HOLD",IF(C20="Create","CEK MER",IF(P20>=Asumsi!$B$27,"FIX","CUT"))))))
J21: =IF(F21="","",IFERROR(E21/D21,"")) | K21: =IF(F21="","",IFERROR(F21/E21,"")) | L21: =IF(F21="","",IFERROR(G21/E21,"")) | M21: =IF(F21="","",IFERROR(F21/G21,"")) | N21: =IF(F21="","",IFERROR(H21/F21,"")) | O21: =IF(F21="","",IF(I21="","",N21*(1-I21))) | P21: =IF(F21="","",IFERROR(N21*Asumsi!$B$11,"")) | Q21: =IF(F21="","",IF(G21<Asumsi!$B$20,"LOW DATA",IF(P21>=Asumsi!$B$16,"SCALE",IF(P21>=Asumsi!$B$26,"HOLD",IF(C21="Create","CEK MER",IF(P21>=Asumsi!$B$27,"FIX","CUT"))))))
J22: =IF(F22="","",IFERROR(E22/D22,"")) | K22: =IF(F22="","",IFERROR(F22/E22,"")) | L22: =IF(F22="","",IFERROR(G22/E22,"")) | M22: =IF(F22="","",IFERROR(F22/G22,"")) | N22: =IF(F22="","",IFERROR(H22/F22,"")) | O22: =IF(F22="","",IF(I22="","",N22*(1-I22))) | P22: =IF(F22="","",IFERROR(N22*Asumsi!$B$11,"")) | Q22: =IF(F22="","",IF(G22<Asumsi!$B$20,"LOW DATA",IF(P22>=Asumsi!$B$16,"SCALE",IF(P22>=Asumsi!$B$26,"HOLD",IF(C22="Create","CEK MER",IF(P22>=Asumsi!$B$27,"FIX","CUT"))))))
J23: =IF(F23="","",IFERROR(E23/D23,"")) | K23: =IF(F23="","",IFERROR(F23/E23,"")) | L23: =IF(F23="","",IFERROR(G23/E23,"")) | M23: =IF(F23="","",IFERROR(F23/G23,"")) | N23: =IF(F23="","",IFERROR(H23/F23,"")) | O23: =IF(F23="","",IF(I23="","",N23*(1-I23))) | P23: =IF(F23="","",IFERROR(N23*Asumsi!$B$11,"")) | Q23: =IF(F23="","",IF(G23<Asumsi!$B$20,"LOW DATA",IF(P23>=Asumsi!$B$16,"SCALE",IF(P23>=Asumsi!$B$26,"HOLD",IF(C23="Create","CEK MER",IF(P23>=Asumsi!$B$27,"FIX","CUT"))))))
J24: =IF(F24="","",IFERROR(E24/D24,"")) | K24: =IF(F24="","",IFERROR(F24/E24,"")) | L24: =IF(F24="","",IFERROR(G24/E24,"")) | M24: =IF(F24="","",IFERROR(F24/G24,"")) | N24: =IF(F24="","",IFERROR(H24/F24,"")) | O24: =IF(F24="","",IF(I24="","",N24*(1-I24))) | P24: =IF(F24="","",IFERROR(N24*Asumsi!$B$11,"")) | Q24: =IF(F24="","",IF(G24<Asumsi!$B$20,"LOW DATA",IF(P24>=Asumsi!$B$16,"SCALE",IF(P24>=Asumsi!$B$26,"HOLD",IF(C24="Create","CEK MER",IF(P24>=Asumsi!$B$27,"FIX","CUT"))))))
... J36: =IF(F36="","",IFERROR(E36/D36,"")) | K36: =IF(F36="","",IFERROR(F36/E36,"")) | L36: =IF(F36="","",IFERROR(G36/E36,"")) | M36: =IF(F36="","",IFERROR(F36/G36,"")) | N36: =IF(F36="","",IFERROR(H36/F36,"")) | O36: =IF(F36="","",IF(I36="","",N36*(1-I36))) | P36: =IF(F36="","",IFERROR(N36*Asumsi!$B$11,"")) | Q36: =IF(F36="","",IF(G36<Asumsi!$B$20,"LOW DATA",IF(P36>=Asumsi!$B$16,"SCALE",IF(P36>=Asumsi!$B$26,"HOLD",IF(C36="Create","CEK MER",IF(P36>=Asumsi!$B$27,"FIX","CUT"))))))
A39: SEARCH TERMS: latihan negative keyword
A41: Search term | B41: Campaign | C41: Klik | D41: Biaya (Rp) | E41: Konversi | F41: CPC (Rp) | G41: CPA (Rp) | H41: Saran aksi
A42: kaos polos premium | B42: Search | Non-Brand Produk | C42: 820 | D42: 3690000 | E42: 41 | F42: =IF(A42="","",IFERROR(D42/C42,"")) -> 4500 | G42: =IF(A42="","",IFERROR(D42/E42,"")) -> 90000 | H42: =IF(A42="","",IF(AND(E42=0,D42>=2*Asumsi!$B$15),"TAMBAH NEGATIF",IF(E42=0,"PANTAU",IF(G42<=Asumsi!$B$15,"PROMOSI KE EXACT",IF(G42>2*Asumsi!$B$15,"TURUNKAN / PINDAH PHRASE","PANTAU"))))) -> PANTAU
A43: kaos polos murah | B43: Search | Non-Brand Produk | C43: 1400 | D43: 5600000 | E43: 18 | F43: =IF(A43="","",IFERROR(D43/C43,"")) -> 4000 | G43: =IF(A43="","",IFERROR(D43/E43,"")) -> 311111.11 | H43: =IF(A43="","",IF(AND(E43=0,D43>=2*Asumsi!$B$15),"TAMBAH NEGATIF",IF(E43=0,"PANTAU",IF(G43<=Asumsi!$B$15,"PROMOSI KE EXACT",IF(G43>2*Asumsi!$B$15,"TURUNKAN / PINDAH PHRASE","PANTAU"))))) -> TURUNKAN / PINDAH PHRASE
A44: grosir kaos polos | B44: Search | Non-Brand Produk | C44: 300 | D44: 1350000 | E44: 22 | F44: =IF(A44="","",IFERROR(D44/C44,"")) -> 4500 | G44: =IF(A44="","",IFERROR(D44/E44,"")) -> 61363.636 | H44: =IF(A44="","",IF(AND(E44=0,D44>=2*Asumsi!$B$15),"TAMBAH NEGATIF",IF(E44=0,"PANTAU",IF(G44<=Asumsi!$B$15,"PROMOSI KE EXACT",IF(G44>2*Asumsi!$B$15,"TURUNKAN / PINDAH PHRASE","PANTAU"))))) -> PANTAU
A45: cara membuat kaos sablon sendiri | B45: Search | Non-Brand Produk | C45: 640 | D45: 2400000 | E45: 0 | F45: =IF(A45="","",IFERROR(D45/C45,"")) -> 3750 | G45: =IF(A45="","",IFERROR(D45/E45,"")) | H45: =IF(A45="","",IF(AND(E45=0,D45>=2*Asumsi!$B$15),"TAMBAH NEGATIF",IF(E45=0,"PANTAU",IF(G45<=Asumsi!$B$15,"PROMOSI KE EXACT",IF(G45>2*Asumsi!$B$15,"TURUNKAN / PINDAH PHRASE","PANTAU"))))) -> TAMBAH NEGATIF
A46: lowongan konveksi | B46: Search | Non-Brand Produk | C46: 210 | D46: 900000 | E46: 0 | F46: =IF(A46="","",IFERROR(D46/C46,"")) -> 4285.7143 | G46: =IF(A46="","",IFERROR(D46/E46,"")) | H46: =IF(A46="","",IF(AND(E46=0,D46>=2*Asumsi!$B$15),"TAMBAH NEGATIF",IF(E46=0,"PANTAU",IF(G46<=Asumsi!$B$15,"PROMOSI KE EXACT",IF(G46>2*Asumsi!$B$15,"TURUNKAN / PINDAH PHRASE","PANTAU"))))) -> TAMBAH NEGATIF
A47: template desain kaos gratis | B47: Search | Non-Brand Produk | C47: 380 | D47: 1500000 | E47: 0 | F47: =IF(A47="","",IFERROR(D47/C47,"")) -> 3947.3684 | G47: =IF(A47="","",IFERROR(D47/E47,"")) | H47: =IF(A47="","",IF(AND(E47=0,D47>=2*Asumsi!$B$15),"TAMBAH NEGATIF",IF(E47=0,"PANTAU",IF(G47<=Asumsi!$B$15,"PROMOSI KE EXACT",IF(G47>2*Asumsi!$B$15,"TURUNKAN / PINDAH PHRASE","PANTAU"))))) -> TAMBAH NEGATIF
A48: hoodie oversize pria | B48: Search | Non-Brand Produk | C48: 520 | D48: 2340000 | E48: 38 | F48: =IF(A48="","",IFERROR(D48/C48,"")) -> 4500 | G48: =IF(A48="","",IFERROR(D48/E48,"")) -> 61578.947 | H48: =IF(A48="","",IF(AND(E48=0,D48>=2*Asumsi!$B$15),"TAMBAH NEGATIF",IF(E48=0,"PANTAU",IF(G48<=Asumsi!$B$15,"PROMOSI KE EXACT",IF(G48>2*Asumsi!$B$15,"TURUNKAN / PINDAH PHRASE","PANTAU"))))) -> PANTAU
A49: hoodie oversize polos hitam | B49: Search | Non-Brand Produk | C49: 260 | D49: 1100000 | E49: 33 | F49: =IF(A49="","",IFERROR(D49/C49,"")) -> 4230.7692 | G49: =IF(A49="","",IFERROR(D49/E49,"")) -> 33333.333 | H49: =IF(A49="","",IF(AND(E49=0,D49>=2*Asumsi!$B$15),"TAMBAH NEGATIF",IF(E49=0,"PANTAU",IF(G49<=Asumsi!$B$15,"PROMOSI KE EXACT",IF(G49>2*Asumsi!$B$15,"TURUNKAN / PINDAH PHRASE","PANTAU"))))) -> PROMOSI KE EXACT
A50: kaos polos cotton combed 30s | B50: Search | Non-Brand Produk | C50: 180 | D50: 720000 | E50: 20 | F50: =IF(A50="","",IFERROR(D50/C50,"")) -> 4000 | G50: =IF(A50="","",IFERROR(D50/E50,"")) -> 36000 | H50: =IF(A50="","",IF(AND(E50=0,D50>=2*Asumsi!$B$15),"TAMBAH NEGATIF",IF(E50=0,"PANTAU",IF(G50<=Asumsi!$B$15,"PROMOSI KE EXACT",IF(G50>2*Asumsi!$B$15,"TURUNKAN / PINDAH PHRASE","PANTAU"))))) -> PROMOSI KE EXACT
A51: jasa sablon kaos satuan | B51: Search | Non-Brand Produk | C51: 450 | D51: 2100000 | E51: 3 | F51: =IF(A51="","",IFERROR(D51/C51,"")) -> 4666.6667 | G51: =IF(A51="","",IFERROR(D51/E51,"")) -> 700000 | H51: =IF(A51="","",IF(AND(E51=0,D51>=2*Asumsi!$B$15),"TAMBAH NEGATIF",IF(E51=0,"PANTAU",IF(G51<=Asumsi!$B$15,"PROMOSI KE EXACT",IF(G51>2*Asumsi!$B$15,"TURUNKAN / PINDAH PHRASE","PANTAU"))))) -> TURUNKAN / PINDAH PHRASE
F52: =IF(A52="","",IFERROR(D52/C52,"")) | G52: =IF(A52="","",IFERROR(D52/E52,"")) | H52: =IF(A52="","",IF(AND(E52=0,D52>=2*Asumsi!$B$15),"TAMBAH NEGATIF",IF(E52=0,"PANTAU",IF(G52<=Asumsi!$B$15,"PROMOSI KE EXACT",IF(G52>2*Asumsi!$B$15,"TURUNKAN / PINDAH PHRASE","PANTAU")))))
F53: =IF(A53="","",IFERROR(D53/C53,"")) | G53: =IF(A53="","",IFERROR(D53/E53,"")) | H53: =IF(A53="","",IF(AND(E53=0,D53>=2*Asumsi!$B$15),"TAMBAH NEGATIF",IF(E53=0,"PANTAU",IF(G53<=Asumsi!$B$15,"PROMOSI KE EXACT",IF(G53>2*Asumsi!$B$15,"TURUNKAN / PINDAH PHRASE","PANTAU")))))
F54: =IF(A54="","",IFERROR(D54/C54,"")) | G54: =IF(A54="","",IFERROR(D54/E54,"")) | H54: =IF(A54="","",IF(AND(E54=0,D54>=2*Asumsi!$B$15),"TAMBAH NEGATIF",IF(E54=0,"PANTAU",IF(G54<=Asumsi!$B$15,"PROMOSI KE EXACT",IF(G54>2*Asumsi!$B$15,"TURUNKAN / PINDAH PHRASE","PANTAU")))))
F55: =IF(A55="","",IFERROR(D55/C55,"")) | G55: =IF(A55="","",IFERROR(D55/E55,"")) | H55: =IF(A55="","",IF(AND(E55=0,D55>=2*Asumsi!$B$15),"TAMBAH NEGATIF",IF(E55=0,"PANTAU",IF(G55<=Asumsi!$B$15,"PROMOSI KE EXACT",IF(G55>2*Asumsi!$B$15,"TURUNKAN / PINDAH PHRASE","PANTAU")))))
A57: Aturan saran: negatif jika 0 konversi dan biaya >= 2x target CPA. Promosi ke exact jika CPA <= target CPA. Turunkan jika CPA > 2x target. Heuristik.

Sheet Meta Ads
A1: Meta Ads: data per iklan (kreatif)
A2: September 2026, data FIKTIF. PROSP = prospecting, RET = retargeting. Kosongkan 3s views untuk iklan gambar.
A5: TOTAL / RASIO | D5: =SUM(D7:D36) -> 43200000 | E5: =SUM(E7:E36) -> 1946000 | H5: =SUM(H7:H36) -> 23340 | I5: =SUM(I7:I36) -> 1990 | J5: =SUM(J7:J36) -> 650 | K5: =SUM(K7:K36) -> 91800000 | L5: =IFERROR(D5/E5*1000,"") -> 22199.383 | O5: =IFERROR(H5/E5,"") -> 0.011993834 | P5: =IFERROR(D5/H5,"") -> 1850.8997 | Q5: =IFERROR(J5/H5,"") -> 0.027849186 | R5: =IFERROR(D5/J5,"") -> 66461.538 | S5: =IFERROR(K5/D5,"") -> 2.125 | T5: =IFERROR(S5*Asumsi!$B$11,"") -> 0.99875
A6: Iklan / Kreatif | B6: Campaign (PROSP/RET) | C6: Format | D6: Biaya (Rp) | E6: Impresi | F6: Jangkauan | G6: Tayang 3 detik | H6: Klik link | I6: Add to cart | J6: Pembelian | K6: Omzet (Rp) | L6: CPM (Rp) | M6: Frekuensi | N6: Hook rate | O6: CTR link | P6: CPC (Rp) | Q6: CVR klik-beli | R6: CPA (Rp) | S6: ROAS | T6: POAS | U6: Verdict
A7: UGC Pain Hook v1 | B7: PROSP | C7: Reels 9:16 | D7: 12000000 | E7: 540000 | F7: 380000 | G7: 183600 | H7: 7020 | I7: 560 | J7: 190 | K7: 28500000 | L7: =IF(D7="","",IFERROR(D7/E7*1000,"")) -> 22222.222 | M7: =IF(D7="","",IFERROR(E7/F7,"")) -> 1.4210526 | N7: =IF(D7="","",IF(G7="","",IFERROR(G7/E7,""))) -> 0.34 | O7: =IF(D7="","",IFERROR(H7/E7,"")) -> 0.013 | P7: =IF(D7="","",IFERROR(D7/H7,"")) -> 1709.4017 | Q7: =IF(D7="","",IFERROR(J7/H7,"")) -> 0.027065527 | R7: =IF(D7="","",IFERROR(D7/J7,"")) -> 63157.895 | S7: =IF(D7="","",IFERROR(K7/D7,"")) -> 2.375 | T7: =IF(D7="","",IFERROR(S7*Asumsi!$B$11,"")) -> 1.11625 | U7: =IF(D7="","",IF(J7<Asumsi!$B$20,"LOW DATA",IF(AND(B7="PROSP",ISNUMBER(M7),M7>=Asumsi!$B$21),"FATIGUE",IF(AND(ISNUMBER(N7),N7>=Asumsi!$B$22,ISNUMBER(Q7),Q7<Asumsi!$B$24),"FIX LANDING",IF(T7>=Asumsi!$B$16,"SCALE",IF(T7>=Asumsi!$B$26,"HOLD",IF(T7>=Asumsi!$B$27,"FIX","CUT"))))))) -> HOLD
A8: Demo Comparison v1 | B8: PROSP | C8: Reels 9:16 | D8: 9000000 | E8: 380000 | F8: 290000 | G8: 98800 | H8: 4560 | I8: 400 | J8: 150 | K8: 22500000 | L8: =IF(D8="","",IFERROR(D8/E8*1000,"")) -> 23684.211 | M8: =IF(D8="","",IFERROR(E8/F8,"")) -> 1.3103448 | N8: =IF(D8="","",IF(G8="","",IFERROR(G8/E8,""))) -> 0.26 | O8: =IF(D8="","",IFERROR(H8/E8,"")) -> 0.012 | P8: =IF(D8="","",IFERROR(D8/H8,"")) -> 1973.6842 | Q8: =IF(D8="","",IFERROR(J8/H8,"")) -> 0.032894737 | R8: =IF(D8="","",IFERROR(D8/J8,"")) -> 60000 | S8: =IF(D8="","",IFERROR(K8/D8,"")) -> 2.5 | T8: =IF(D8="","",IFERROR(S8*Asumsi!$B$11,"")) -> 1.175 | U8: =IF(D8="","",IF(J8<Asumsi!$B$20,"LOW DATA",IF(AND(B8="PROSP",ISNUMBER(M8),M8>=Asumsi!$B$21),"FATIGUE",IF(AND(ISNUMBER(N8),N8>=Asumsi!$B$22,ISNUMBER(Q8),Q8<Asumsi!$B$24),"FIX LANDING",IF(T8>=Asumsi!$B$16,"SCALE",IF(T8>=Asumsi!$B$26,"HOLD",IF(T8>=Asumsi!$B$27,"FIX","CUT"))))))) -> HOLD
A9: UGC Pain Hook v0 (lama) | B9: PROSP | C9: Reels 9:16 | D9: 7500000 | E9: 336000 | F9: 80000 | G9: 60480 | H9: 1680 | I9: 90 | J9: 28 | K9: 4200000 | L9: =IF(D9="","",IFERROR(D9/E9*1000,"")) -> 22321.429 | M9: =IF(D9="","",IFERROR(E9/F9,"")) -> 4.2 | N9: =IF(D9="","",IF(G9="","",IFERROR(G9/E9,""))) -> 0.18 | O9: =IF(D9="","",IFERROR(H9/E9,"")) -> 0.005 | P9: =IF(D9="","",IFERROR(D9/H9,"")) -> 4464.2857 | Q9: =IF(D9="","",IFERROR(J9/H9,"")) -> 0.016666667 | R9: =IF(D9="","",IFERROR(D9/J9,"")) -> 267857.14 | S9: =IF(D9="","",IFERROR(K9/D9,"")) -> 0.56 | T9: =IF(D9="","",IFERROR(S9*Asumsi!$B$11,"")) -> 0.2632 | U9: =IF(D9="","",IF(J9<Asumsi!$B$20,"LOW DATA",IF(AND(B9="PROSP",ISNUMBER(M9),M9>=Asumsi!$B$21),"FATIGUE",IF(AND(ISNUMBER(N9),N9>=Asumsi!$B$22,ISNUMBER(Q9),Q9<Asumsi!$B$24),"FIX LANDING",IF(T9>=Asumsi!$B$16,"SCALE",IF(T9>=Asumsi!$B$26,"HOLD",IF(T9>=Asumsi!$B$27,"FIX","CUT"))))))) -> FATIGUE
A10: Founder Story | B10: PROSP | C10: Video 4:5 | D10: 3000000 | E10: 150000 | F10: 120000 | G10: 54000 | H10: 2250 | I10: 50 | J10: 9 | K10: 1350000 | L10: =IF(D10="","",IFERROR(D10/E10*1000,"")) -> 20000 | M10: =IF(D10="","",IFERROR(E10/F10,"")) -> 1.25 | N10: =IF(D10="","",IF(G10="","",IFERROR(G10/E10,""))) -> 0.36 | O10: =IF(D10="","",IFERROR(H10/E10,"")) -> 0.015 | P10: =IF(D10="","",IFERROR(D10/H10,"")) -> 1333.3333 | Q10: =IF(D10="","",IFERROR(J10/H10,"")) -> 0.004 | R10: =IF(D10="","",IFERROR(D10/J10,"")) -> 333333.33 | S10: =IF(D10="","",IFERROR(K10/D10,"")) -> 0.45 | T10: =IF(D10="","",IFERROR(S10*Asumsi!$B$11,"")) -> 0.2115 | U10: =IF(D10="","",IF(J10<Asumsi!$B$20,"LOW DATA",IF(AND(B10="PROSP",ISNUMBER(M10),M10>=Asumsi!$B$21),"FATIGUE",IF(AND(ISNUMBER(N10),N10>=Asumsi!$B$22,ISNUMBER(Q10),Q10<Asumsi!$B$24),"FIX LANDING",IF(T10>=Asumsi!$B$16,"SCALE",IF(T10>=Asumsi!$B$26,"HOLD",IF(T10>=Asumsi!$B$27,"FIX","CUT"))))))) -> FIX LANDING
A11: Testimonial Static | B11: PROSP | C11: Gambar 4:5 | D11: 6000000 | E11: 300000 | F11: 158000 | H11: 3300 | I11: 270 | J11: 110 | K11: 10800000 | L11: =IF(D11="","",IFERROR(D11/E11*1000,"")) -> 20000 | M11: =IF(D11="","",IFERROR(E11/F11,"")) -> 1.8987342 | N11: =IF(D11="","",IF(G11="","",IFERROR(G11/E11,""))) | O11: =IF(D11="","",IFERROR(H11/E11,"")) -> 0.011 | P11: =IF(D11="","",IFERROR(D11/H11,"")) -> 1818.1818 | Q11: =IF(D11="","",IFERROR(J11/H11,"")) -> 0.033333333 | R11: =IF(D11="","",IFERROR(D11/J11,"")) -> 54545.455 | S11: =IF(D11="","",IFERROR(K11/D11,"")) -> 1.8 | T11: =IF(D11="","",IFERROR(S11*Asumsi!$B$11,"")) -> 0.846 | U11: =IF(D11="","",IF(J11<Asumsi!$B$20,"LOW DATA",IF(AND(B11="PROSP",ISNUMBER(M11),M11>=Asumsi!$B$21),"FATIGUE",IF(AND(ISNUMBER(N11),N11>=Asumsi!$B$22,ISNUMBER(Q11),Q11<Asumsi!$B$24),"FIX LANDING",IF(T11>=Asumsi!$B$16,"SCALE",IF(T11>=Asumsi!$B$26,"HOLD",IF(T11>=Asumsi!$B$27,"FIX","CUT"))))))) -> FIX
A12: Cart Abandoner 7 hari | B12: RET | C12: Carousel | D12: 5000000 | E12: 210000 | F12: 75000 | G12: 50400 | H12: 4200 | I12: 600 | J12: 160 | K12: 24000000 | L12: =IF(D12="","",IFERROR(D12/E12*1000,"")) -> 23809.524 | M12: =IF(D12="","",IFERROR(E12/F12,"")) -> 2.8 | N12: =IF(D12="","",IF(G12="","",IFERROR(G12/E12,""))) -> 0.24 | O12: =IF(D12="","",IFERROR(H12/E12,"")) -> 0.02 | P12: =IF(D12="","",IFERROR(D12/H12,"")) -> 1190.4762 | Q12: =IF(D12="","",IFERROR(J12/H12,"")) -> 0.038095238 | R12: =IF(D12="","",IFERROR(D12/J12,"")) -> 31250 | S12: =IF(D12="","",IFERROR(K12/D12,"")) -> 4.8 | T12: =IF(D12="","",IFERROR(S12*Asumsi!$B$11,"")) -> 2.256 | U12: =IF(D12="","",IF(J12<Asumsi!$B$20,"LOW DATA",IF(AND(B12="PROSP",ISNUMBER(M12),M12>=Asumsi!$B$21),"FATIGUE",IF(AND(ISNUMBER(N12),N12>=Asumsi!$B$22,ISNUMBER(Q12),Q12<Asumsi!$B$24),"FIX LANDING",IF(T12>=Asumsi!$B$16,"SCALE",IF(T12>=Asumsi!$B$26,"HOLD",IF(T12>=Asumsi!$B$27,"FIX","CUT"))))))) -> SCALE
A13: Carousel Bundle Hemat (tes baru) | B13: PROSP | C13: Carousel | D13: 700000 | E13: 30000 | F13: 26000 | G13: 7500 | H13: 330 | I13: 20 | J13: 3 | K13: 450000 | L13: =IF(D13="","",IFERROR(D13/E13*1000,"")) -> 23333.333 | M13: =IF(D13="","",IFERROR(E13/F13,"")) -> 1.1538462 | N13: =IF(D13="","",IF(G13="","",IFERROR(G13/E13,""))) -> 0.25 | O13: =IF(D13="","",IFERROR(H13/E13,"")) -> 0.011 | P13: =IF(D13="","",IFERROR(D13/H13,"")) -> 2121.2121 | Q13: =IF(D13="","",IFERROR(J13/H13,"")) -> 0.0090909091 | R13: =IF(D13="","",IFERROR(D13/J13,"")) -> 233333.33 | S13: =IF(D13="","",IFERROR(K13/D13,"")) -> 0.64285714 | T13: =IF(D13="","",IFERROR(S13*Asumsi!$B$11,"")) -> 0.30214286 | U13: =IF(D13="","",IF(J13<Asumsi!$B$20,"LOW DATA",IF(AND(B13="PROSP",ISNUMBER(M13),M13>=Asumsi!$B$21),"FATIGUE",IF(AND(ISNUMBER(N13),N13>=Asumsi!$B$22,ISNUMBER(Q13),Q13<Asumsi!$B$24),"FIX LANDING",IF(T13>=Asumsi!$B$16,"SCALE",IF(T13>=Asumsi!$B$26,"HOLD",IF(T13>=Asumsi!$B$27,"FIX","CUT"))))))) -> LOW DATA
L14: =IF(D14="","",IFERROR(D14/E14*1000,"")) | M14: =IF(D14="","",IFERROR(E14/F14,"")) | N14: =IF(D14="","",IF(G14="","",IFERROR(G14/E14,""))) | O14: =IF(D14="","",IFERROR(H14/E14,"")) | P14: =IF(D14="","",IFERROR(D14/H14,"")) | Q14: =IF(D14="","",IFERROR(J14/H14,"")) | R14: =IF(D14="","",IFERROR(D14/J14,"")) | S14: =IF(D14="","",IFERROR(K14/D14,"")) | T14: =IF(D14="","",IFERROR(S14*Asumsi!$B$11,"")) | U14: =IF(D14="","",IF(J14<Asumsi!$B$20,"LOW DATA",IF(AND(B14="PROSP",ISNUMBER(M14),M14>=Asumsi!$B$21),"FATIGUE",IF(AND(ISNUMBER(N14),N14>=Asumsi!$B$22,ISNUMBER(Q14),Q14<Asumsi!$B$24),"FIX LANDING",IF(T14>=Asumsi!$B$16,"SCALE",IF(T14>=Asumsi!$B$26,"HOLD",IF(T14>=Asumsi!$B$27,"FIX","CUT")))))))
L15: =IF(D15="","",IFERROR(D15/E15*1000,"")) | M15: =IF(D15="","",IFERROR(E15/F15,"")) | N15: =IF(D15="","",IF(G15="","",IFERROR(G15/E15,""))) | O15: =IF(D15="","",IFERROR(H15/E15,"")) | P15: =IF(D15="","",IFERROR(D15/H15,"")) | Q15: =IF(D15="","",IFERROR(J15/H15,"")) | R15: =IF(D15="","",IFERROR(D15/J15,"")) | S15: =IF(D15="","",IFERROR(K15/D15,"")) | T15: =IF(D15="","",IFERROR(S15*Asumsi!$B$11,"")) | U15: =IF(D15="","",IF(J15<Asumsi!$B$20,"LOW DATA",IF(AND(B15="PROSP",ISNUMBER(M15),M15>=Asumsi!$B$21),"FATIGUE",IF(AND(ISNUMBER(N15),N15>=Asumsi!$B$22,ISNUMBER(Q15),Q15<Asumsi!$B$24),"FIX LANDING",IF(T15>=Asumsi!$B$16,"SCALE",IF(T15>=Asumsi!$B$26,"HOLD",IF(T15>=Asumsi!$B$27,"FIX","CUT")))))))
L16: =IF(D16="","",IFERROR(D16/E16*1000,"")) | M16: =IF(D16="","",IFERROR(E16/F16,"")) | N16: =IF(D16="","",IF(G16="","",IFERROR(G16/E16,""))) | O16: =IF(D16="","",IFERROR(H16/E16,"")) | P16: =IF(D16="","",IFERROR(D16/H16,"")) | Q16: =IF(D16="","",IFERROR(J16/H16,"")) | R16: =IF(D16="","",IFERROR(D16/J16,"")) | S16: =IF(D16="","",IFERROR(K16/D16,"")) | T16: =IF(D16="","",IFERROR(S16*Asumsi!$B$11,"")) | U16: =IF(D16="","",IF(J16<Asumsi!$B$20,"LOW DATA",IF(AND(B16="PROSP",ISNUMBER(M16),M16>=Asumsi!$B$21),"FATIGUE",IF(AND(ISNUMBER(N16),N16>=Asumsi!$B$22,ISNUMBER(Q16),Q16<Asumsi!$B$24),"FIX LANDING",IF(T16>=Asumsi!$B$16,"SCALE",IF(T16>=Asumsi!$B$26,"HOLD",IF(T16>=Asumsi!$B$27,"FIX","CUT")))))))
L17: =IF(D17="","",IFERROR(D17/E17*1000,"")) | M17: =IF(D17="","",IFERROR(E17/F17,"")) | N17: =IF(D17="","",IF(G17="","",IFERROR(G17/E17,""))) | O17: =IF(D17="","",IFERROR(H17/E17,"")) | P17: =IF(D17="","",IFERROR(D17/H17,"")) | Q17: =IF(D17="","",IFERROR(J17/H17,"")) | R17: =IF(D17="","",IFERROR(D17/J17,"")) | S17: =IF(D17="","",IFERROR(K17/D17,"")) | T17: =IF(D17="","",IFERROR(S17*Asumsi!$B$11,"")) | U17: =IF(D17="","",IF(J17<Asumsi!$B$20,"LOW DATA",IF(AND(B17="PROSP",ISNUMBER(M17),M17>=Asumsi!$B$21),"FATIGUE",IF(AND(ISNUMBER(N17),N17>=Asumsi!$B$22,ISNUMBER(Q17),Q17<Asumsi!$B$24),"FIX LANDING",IF(T17>=Asumsi!$B$16,"SCALE",IF(T17>=Asumsi!$B$26,"HOLD",IF(T17>=Asumsi!$B$27,"FIX","CUT")))))))
L18: =IF(D18="","",IFERROR(D18/E18*1000,"")) | M18: =IF(D18="","",IFERROR(E18/F18,"")) | N18: =IF(D18="","",IF(G18="","",IFERROR(G18/E18,""))) | O18: =IF(D18="","",IFERROR(H18/E18,"")) | P18: =IF(D18="","",IFERROR(D18/H18,"")) | Q18: =IF(D18="","",IFERROR(J18/H18,"")) | R18: =IF(D18="","",IFERROR(D18/J18,"")) | S18: =IF(D18="","",IFERROR(K18/D18,"")) | T18: =IF(D18="","",IFERROR(S18*Asumsi!$B$11,"")) | U18: =IF(D18="","",IF(J18<Asumsi!$B$20,"LOW DATA",IF(AND(B18="PROSP",ISNUMBER(M18),M18>=Asumsi!$B$21),"FATIGUE",IF(AND(ISNUMBER(N18),N18>=Asumsi!$B$22,ISNUMBER(Q18),Q18<Asumsi!$B$24),"FIX LANDING",IF(T18>=Asumsi!$B$16,"SCALE",IF(T18>=Asumsi!$B$26,"HOLD",IF(T18>=Asumsi!$B$27,"FIX","CUT")))))))
L19: =IF(D19="","",IFERROR(D19/E19*1000,"")) | M19: =IF(D19="","",IFERROR(E19/F19,"")) | N19: =IF(D19="","",IF(G19="","",IFERROR(G19/E19,""))) | O19: =IF(D19="","",IFERROR(H19/E19,"")) | P19: =IF(D19="","",IFERROR(D19/H19,"")) | Q19: =IF(D19="","",IFERROR(J19/H19,"")) | R19: =IF(D19="","",IFERROR(D19/J19,"")) | S19: =IF(D19="","",IFERROR(K19/D19,"")) | T19: =IF(D19="","",IFERROR(S19*Asumsi!$B$11,"")) | U19: =IF(D19="","",IF(J19<Asumsi!$B$20,"LOW DATA",IF(AND(B19="PROSP",ISNUMBER(M19),M19>=Asumsi!$B$21),"FATIGUE",IF(AND(ISNUMBER(N19),N19>=Asumsi!$B$22,ISNUMBER(Q19),Q19<Asumsi!$B$24),"FIX LANDING",IF(T19>=Asumsi!$B$16,"SCALE",IF(T19>=Asumsi!$B$26,"HOLD",IF(T19>=Asumsi!$B$27,"FIX","CUT")))))))
L20: =IF(D20="","",IFERROR(D20/E20*1000,"")) | M20: =IF(D20="","",IFERROR(E20/F20,"")) | N20: =IF(D20="","",IF(G20="","",IFERROR(G20/E20,""))) | O20: =IF(D20="","",IFERROR(H20/E20,"")) | P20: =IF(D20="","",IFERROR(D20/H20,"")) | Q20: =IF(D20="","",IFERROR(J20/H20,"")) | R20: =IF(D20="","",IFERROR(D20/J20,"")) | S20: =IF(D20="","",IFERROR(K20/D20,"")) | T20: =IF(D20="","",IFERROR(S20*Asumsi!$B$11,"")) | U20: =IF(D20="","",IF(J20<Asumsi!$B$20,"LOW DATA",IF(AND(B20="PROSP",ISNUMBER(M20),M20>=Asumsi!$B$21),"FATIGUE",IF(AND(ISNUMBER(N20),N20>=Asumsi!$B$22,ISNUMBER(Q20),Q20<Asumsi!$B$24),"FIX LANDING",IF(T20>=Asumsi!$B$16,"SCALE",IF(T20>=Asumsi!$B$26,"HOLD",IF(T20>=Asumsi!$B$27,"FIX","CUT")))))))
L21: =IF(D21="","",IFERROR(D21/E21*1000,"")) | M21: =IF(D21="","",IFERROR(E21/F21,"")) | N21: =IF(D21="","",IF(G21="","",IFERROR(G21/E21,""))) | O21: =IF(D21="","",IFERROR(H21/E21,"")) | P21: =IF(D21="","",IFERROR(D21/H21,"")) | Q21: =IF(D21="","",IFERROR(J21/H21,"")) | R21: =IF(D21="","",IFERROR(D21/J21,"")) | S21: =IF(D21="","",IFERROR(K21/D21,"")) | T21: =IF(D21="","",IFERROR(S21*Asumsi!$B$11,"")) | U21: =IF(D21="","",IF(J21<Asumsi!$B$20,"LOW DATA",IF(AND(B21="PROSP",ISNUMBER(M21),M21>=Asumsi!$B$21),"FATIGUE",IF(AND(ISNUMBER(N21),N21>=Asumsi!$B$22,ISNUMBER(Q21),Q21<Asumsi!$B$24),"FIX LANDING",IF(T21>=Asumsi!$B$16,"SCALE",IF(T21>=Asumsi!$B$26,"HOLD",IF(T21>=Asumsi!$B$27,"FIX","CUT")))))))
L22: =IF(D22="","",IFERROR(D22/E22*1000,"")) | M22: =IF(D22="","",IFERROR(E22/F22,"")) | N22: =IF(D22="","",IF(G22="","",IFERROR(G22/E22,""))) | O22: =IF(D22="","",IFERROR(H22/E22,"")) | P22: =IF(D22="","",IFERROR(D22/H22,"")) | Q22: =IF(D22="","",IFERROR(J22/H22,"")) | R22: =IF(D22="","",IFERROR(D22/J22,"")) | S22: =IF(D22="","",IFERROR(K22/D22,"")) | T22: =IF(D22="","",IFERROR(S22*Asumsi!$B$11,"")) | U22: =IF(D22="","",IF(J22<Asumsi!$B$20,"LOW DATA",IF(AND(B22="PROSP",ISNUMBER(M22),M22>=Asumsi!$B$21),"FATIGUE",IF(AND(ISNUMBER(N22),N22>=Asumsi!$B$22,ISNUMBER(Q22),Q22<Asumsi!$B$24),"FIX LANDING",IF(T22>=Asumsi!$B$16,"SCALE",IF(T22>=Asumsi!$B$26,"HOLD",IF(T22>=Asumsi!$B$27,"FIX","CUT")))))))
L23: =IF(D23="","",IFERROR(D23/E23*1000,"")) | M23: =IF(D23="","",IFERROR(E23/F23,"")) | N23: =IF(D23="","",IF(G23="","",IFERROR(G23/E23,""))) | O23: =IF(D23="","",IFERROR(H23/E23,"")) | P23: =IF(D23="","",IFERROR(D23/H23,"")) | Q23: =IF(D23="","",IFERROR(J23/H23,"")) | R23: =IF(D23="","",IFERROR(D23/J23,"")) | S23: =IF(D23="","",IFERROR(K23/D23,"")) | T23: =IF(D23="","",IFERROR(S23*Asumsi!$B$11,"")) | U23: =IF(D23="","",IF(J23<Asumsi!$B$20,"LOW DATA",IF(AND(B23="PROSP",ISNUMBER(M23),M23>=Asumsi!$B$21),"FATIGUE",IF(AND(ISNUMBER(N23),N23>=Asumsi!$B$22,ISNUMBER(Q23),Q23<Asumsi!$B$24),"FIX LANDING",IF(T23>=Asumsi!$B$16,"SCALE",IF(T23>=Asumsi!$B$26,"HOLD",IF(T23>=Asumsi!$B$27,"FIX","CUT")))))))
L24: =IF(D24="","",IFERROR(D24/E24*1000,"")) | M24: =IF(D24="","",IFERROR(E24/F24,"")) | N24: =IF(D24="","",IF(G24="","",IFERROR(G24/E24,""))) | O24: =IF(D24="","",IFERROR(H24/E24,"")) | P24: =IF(D24="","",IFERROR(D24/H24,"")) | Q24: =IF(D24="","",IFERROR(J24/H24,"")) | R24: =IF(D24="","",IFERROR(D24/J24,"")) | S24: =IF(D24="","",IFERROR(K24/D24,"")) | T24: =IF(D24="","",IFERROR(S24*Asumsi!$B$11,"")) | U24: =IF(D24="","",IF(J24<Asumsi!$B$20,"LOW DATA",IF(AND(B24="PROSP",ISNUMBER(M24),M24>=Asumsi!$B$21),"FATIGUE",IF(AND(ISNUMBER(N24),N24>=Asumsi!$B$22,ISNUMBER(Q24),Q24<Asumsi!$B$24),"FIX LANDING",IF(T24>=Asumsi!$B$16,"SCALE",IF(T24>=Asumsi!$B$26,"HOLD",IF(T24>=Asumsi!$B$27,"FIX","CUT")))))))
L25: =IF(D25="","",IFERROR(D25/E25*1000,"")) | M25: =IF(D25="","",IFERROR(E25/F25,"")) | N25: =IF(D25="","",IF(G25="","",IFERROR(G25/E25,""))) | O25: =IF(D25="","",IFERROR(H25/E25,"")) | P25: =IF(D25="","",IFERROR(D25/H25,"")) | Q25: =IF(D25="","",IFERROR(J25/H25,"")) | R25: =IF(D25="","",IFERROR(D25/J25,"")) | S25: =IF(D25="","",IFERROR(K25/D25,"")) | T25: =IF(D25="","",IFERROR(S25*Asumsi!$B$11,"")) | U25: =IF(D25="","",IF(J25<Asumsi!$B$20,"LOW DATA",IF(AND(B25="PROSP",ISNUMBER(M25),M25>=Asumsi!$B$21),"FATIGUE",IF(AND(ISNUMBER(N25),N25>=Asumsi!$B$22,ISNUMBER(Q25),Q25<Asumsi!$B$24),"FIX LANDING",IF(T25>=Asumsi!$B$16,"SCALE",IF(T25>=Asumsi!$B$26,"HOLD",IF(T25>=Asumsi!$B$27,"FIX","CUT")))))))
... L36: =IF(D36="","",IFERROR(D36/E36*1000,"")) | M36: =IF(D36="","",IFERROR(E36/F36,"")) | N36: =IF(D36="","",IF(G36="","",IFERROR(G36/E36,""))) | O36: =IF(D36="","",IFERROR(H36/E36,"")) | P36: =IF(D36="","",IFERROR(D36/H36,"")) | Q36: =IF(D36="","",IFERROR(J36/H36,"")) | R36: =IF(D36="","",IFERROR(D36/J36,"")) | S36: =IF(D36="","",IFERROR(K36/D36,"")) | T36: =IF(D36="","",IFERROR(S36*Asumsi!$B$11,"")) | U36: =IF(D36="","",IF(J36<Asumsi!$B$20,"LOW DATA",IF(AND(B36="PROSP",ISNUMBER(M36),M36>=Asumsi!$B$21),"FATIGUE",IF(AND(ISNUMBER(N36),N36>=Asumsi!$B$22,ISNUMBER(Q36),Q36<Asumsi!$B$24),"FIX LANDING",IF(T36>=Asumsi!$B$16,"SCALE",IF(T36>=Asumsi!$B$26,"HOLD",IF(T36>=Asumsi!$B$27,"FIX","CUT")))))))
A38: Cara baca: FATIGUE = frekuensi prospecting >= batas. FIX LANDING = hook bagus tapi klik jarang jadi beli. Ambang ada di sheet Asumsi.

Sheet TikTok Ads
A1: TikTok Ads: data per kreatif
A2: September 2026, data FIKTIF. Isi CTR minggu lalu untuk deteksi fatigue.
A5: TOTAL / RASIO | D5: =SUM(D7:D36) -> 28600000 | E5: =SUM(E7:E36) -> 3875000 | H5: =SUM(H7:H36) -> 26985 | I5: =SUM(I7:I36) -> 576 | J5: =SUM(J7:J36) -> 86400000 | L5: =IFERROR(D5/E5*1000,"") -> 7380.6452 | O5: =IFERROR(H5/E5,"") -> 0.006963871 | P5: =IFERROR(I5/H5,"") -> 0.021345192 | Q5: =IFERROR(D5/I5,"") -> 49652.778 | R5: =IFERROR(J5/D5,"") -> 3.020979 | S5: =IFERROR(R5*Asumsi!$B$11,"") -> 1.4198601
A6: Kreatif | B6: Tipe | C6: Campaign (TEST/SCALE/RET) | D6: Biaya (Rp) | E6: Impresi | F6: Tayang 2 detik | G6: Tayang 6 detik | H6: Klik | I6: Pembelian | J6: Omzet (Rp) | K6: CTR minggu lalu | L6: CPM (Rp) | M6: Hook rate (2s/impresi) | N6: Hold rate (6s/2s) | O6: CTR | P6: CVR | Q6: CPA (Rp) | R6: ROAS | S6: POAS | T6: Verdict
A7: Skit Pain Point v1 | B7: Spark Ads | C7: SCALE | D7: 8000000 | E7: 900000 | F7: 270000 | G7: 126000 | H7: 9000 | I7: 210 | J7: 31500000 | K7: 0.0095 | L7: =IF(D7="","",IFERROR(D7/E7*1000,"")) -> 8888.8889 | M7: =IF(D7="","",IF(F7="","",IFERROR(F7/E7,""))) -> 0.3 | N7: =IF(D7="","",IF(G7="","",IFERROR(G7/F7,""))) -> 0.46666667 | O7: =IF(D7="","",IFERROR(H7/E7,"")) -> 0.01 | P7: =IF(D7="","",IFERROR(I7/H7,"")) -> 0.023333333 | Q7: =IF(D7="","",IFERROR(D7/I7,"")) -> 38095.238 | R7: =IF(D7="","",IFERROR(J7/D7,"")) -> 3.9375 | S7: =IF(D7="","",IFERROR(R7*Asumsi!$B$11,"")) -> 1.850625 | T7: =IF(D7="","",IF(I7<Asumsi!$B$20,"LOW DATA",IF(AND(ISNUMBER(K7),ISNUMBER(O7),N(K7)>0,O7/N(K7)<Asumsi!$B$25),"FATIGUE",IF(AND(ISNUMBER(M7),M7>=Asumsi!$B$22,ISNUMBER(O7),O7<Asumsi!$B$23),"FIX CTA/BODY",IF(AND(ISNUMBER(M7),M7<Asumsi!$B$22,S7<Asumsi!$B$16),"FIX HOOK",IF(S7>=Asumsi!$B$16,"SCALE",IF(S7>=Asumsi!$B$26,"HOLD",IF(S7>=Asumsi!$B$27,"FIX","CUT")))))))) -> SCALE
A8: Creator Review (Spark) | B8: Spark Ads | C8: SCALE | D8: 6000000 | E8: 700000 | F8: 210000 | G8: 105000 | H8: 6300 | I8: 120 | J8: 18000000 | K8: 0.01 | L8: =IF(D8="","",IFERROR(D8/E8*1000,"")) -> 8571.4286 | M8: =IF(D8="","",IF(F8="","",IFERROR(F8/E8,""))) -> 0.3 | N8: =IF(D8="","",IF(G8="","",IFERROR(G8/F8,""))) -> 0.5 | O8: =IF(D8="","",IFERROR(H8/E8,"")) -> 0.009 | P8: =IF(D8="","",IFERROR(I8/H8,"")) -> 0.019047619 | Q8: =IF(D8="","",IFERROR(D8/I8,"")) -> 50000 | R8: =IF(D8="","",IFERROR(J8/D8,"")) -> 3 | S8: =IF(D8="","",IFERROR(R8*Asumsi!$B$11,"")) -> 1.41 | T8: =IF(D8="","",IF(I8<Asumsi!$B$20,"LOW DATA",IF(AND(ISNUMBER(K8),ISNUMBER(O8),N(K8)>0,O8/N(K8)<Asumsi!$B$25),"FATIGUE",IF(AND(ISNUMBER(M8),M8>=Asumsi!$B$22,ISNUMBER(O8),O8<Asumsi!$B$23),"FIX CTA/BODY",IF(AND(ISNUMBER(M8),M8<Asumsi!$B$22,S8<Asumsi!$B$16),"FIX HOOK",IF(S8>=Asumsi!$B$16,"SCALE",IF(S8>=Asumsi!$B$26,"HOLD",IF(S8>=Asumsi!$B$27,"FIX","CUT")))))))) -> SCALE
A9: Demo Produk ASMR | B9: Non-Spark | C9: TEST | D9: 4000000 | E9: 550000 | F9: 88000 | G9: 44000 | H9: 2750 | I9: 65 | J9: 9750000 | K9: 0.005 | L9: =IF(D9="","",IFERROR(D9/E9*1000,"")) -> 7272.7273 | M9: =IF(D9="","",IF(F9="","",IFERROR(F9/E9,""))) -> 0.16 | N9: =IF(D9="","",IF(G9="","",IFERROR(G9/F9,""))) -> 0.5 | O9: =IF(D9="","",IFERROR(H9/E9,"")) -> 0.005 | P9: =IF(D9="","",IFERROR(I9/H9,"")) -> 0.023636364 | Q9: =IF(D9="","",IFERROR(D9/I9,"")) -> 61538.462 | R9: =IF(D9="","",IFERROR(J9/D9,"")) -> 2.4375 | S9: =IF(D9="","",IFERROR(R9*Asumsi!$B$11,"")) -> 1.145625 | T9: =IF(D9="","",IF(I9<Asumsi!$B$20,"LOW DATA",IF(AND(ISNUMBER(K9),ISNUMBER(O9),N(K9)>0,O9/N(K9)<Asumsi!$B$25),"FATIGUE",IF(AND(ISNUMBER(M9),M9>=Asumsi!$B$22,ISNUMBER(O9),O9<Asumsi!$B$23),"FIX CTA/BODY",IF(AND(ISNUMBER(M9),M9<Asumsi!$B$22,S9<Asumsi!$B$16),"FIX HOOK",IF(S9>=Asumsi!$B$16,"SCALE",IF(S9>=Asumsi!$B$26,"HOLD",IF(S9>=Asumsi!$B$27,"FIX","CUT")))))))) -> FIX HOOK
A10: Trend Sound Dance | B10: Non-Spark | C10: TEST | D10: 3000000 | E10: 800000 | F10: 320000 | G10: 96000 | H10: 1600 | I10: 18 | J10: 2700000 | K10: 0.002 | L10: =IF(D10="","",IFERROR(D10/E10*1000,"")) -> 3750 | M10: =IF(D10="","",IF(F10="","",IFERROR(F10/E10,""))) -> 0.4 | N10: =IF(D10="","",IF(G10="","",IFERROR(G10/F10,""))) -> 0.3 | O10: =IF(D10="","",IFERROR(H10/E10,"")) -> 0.002 | P10: =IF(D10="","",IFERROR(I10/H10,"")) -> 0.01125 | Q10: =IF(D10="","",IFERROR(D10/I10,"")) -> 166666.67 | R10: =IF(D10="","",IFERROR(J10/D10,"")) -> 0.9 | S10: =IF(D10="","",IFERROR(R10*Asumsi!$B$11,"")) -> 0.423 | T10: =IF(D10="","",IF(I10<Asumsi!$B$20,"LOW DATA",IF(AND(ISNUMBER(K10),ISNUMBER(O10),N(K10)>0,O10/N(K10)<Asumsi!$B$25),"FATIGUE",IF(AND(ISNUMBER(M10),M10>=Asumsi!$B$22,ISNUMBER(O10),O10<Asumsi!$B$23),"FIX CTA/BODY",IF(AND(ISNUMBER(M10),M10<Asumsi!$B$22,S10<Asumsi!$B$16),"FIX HOOK",IF(S10>=Asumsi!$B$16,"SCALE",IF(S10>=Asumsi!$B$26,"HOLD",IF(S10>=Asumsi!$B$27,"FIX","CUT")))))))) -> FIX CTA/BODY
A11: Promo Flash Sale v3 (hari ke-18) | B11: Non-Spark | C11: SCALE | D11: 5000000 | E11: 650000 | F11: 156000 | G11: 70200 | H11: 3575 | I11: 70 | J11: 10500000 | K11: 0.011 | L11: =IF(D11="","",IFERROR(D11/E11*1000,"")) -> 7692.3077 | M11: =IF(D11="","",IF(F11="","",IFERROR(F11/E11,""))) -> 0.24 | N11: =IF(D11="","",IF(G11="","",IFERROR(G11/F11,""))) -> 0.45 | O11: =IF(D11="","",IFERROR(H11/E11,"")) -> 0.0055 | P11: =IF(D11="","",IFERROR(I11/H11,"")) -> 0.01958042 | Q11: =IF(D11="","",IFERROR(D11/I11,"")) -> 71428.571 | R11: =IF(D11="","",IFERROR(J11/D11,"")) -> 2.1 | S11: =IF(D11="","",IFERROR(R11*Asumsi!$B$11,"")) -> 0.987 | T11: =IF(D11="","",IF(I11<Asumsi!$B$20,"LOW DATA",IF(AND(ISNUMBER(K11),ISNUMBER(O11),N(K11)>0,O11/N(K11)<Asumsi!$B$25),"FATIGUE",IF(AND(ISNUMBER(M11),M11>=Asumsi!$B$22,ISNUMBER(O11),O11<Asumsi!$B$23),"FIX CTA/BODY",IF(AND(ISNUMBER(M11),M11<Asumsi!$B$22,S11<Asumsi!$B$16),"FIX HOOK",IF(S11>=Asumsi!$B$16,"SCALE",IF(S11>=Asumsi!$B$26,"HOLD",IF(S11>=Asumsi!$B$27,"FIX","CUT")))))))) -> FATIGUE
A12: Retargeting Penonton Video | B12: Non-Spark | C12: RET | D12: 2000000 | E12: 180000 | F12: 50400 | G12: 27000 | H12: 3000 | I12: 90 | J12: 13500000 | K12: 0.016 | L12: =IF(D12="","",IFERROR(D12/E12*1000,"")) -> 11111.111 | M12: =IF(D12="","",IF(F12="","",IFERROR(F12/E12,""))) -> 0.28 | N12: =IF(D12="","",IF(G12="","",IFERROR(G12/F12,""))) -> 0.53571429 | O12: =IF(D12="","",IFERROR(H12/E12,"")) -> 0.016666667 | P12: =IF(D12="","",IFERROR(I12/H12,"")) -> 0.03 | Q12: =IF(D12="","",IFERROR(D12/I12,"")) -> 22222.222 | R12: =IF(D12="","",IFERROR(J12/D12,"")) -> 6.75 | S12: =IF(D12="","",IFERROR(R12*Asumsi!$B$11,"")) -> 3.1725 | T12: =IF(D12="","",IF(I12<Asumsi!$B$20,"LOW DATA",IF(AND(ISNUMBER(K12),ISNUMBER(O12),N(K12)>0,O12/N(K12)<Asumsi!$B$25),"FATIGUE",IF(AND(ISNUMBER(M12),M12>=Asumsi!$B$22,ISNUMBER(O12),O12<Asumsi!$B$23),"FIX CTA/BODY",IF(AND(ISNUMBER(M12),M12<Asumsi!$B$22,S12<Asumsi!$B$16),"FIX HOOK",IF(S12>=Asumsi!$B$16,"SCALE",IF(S12>=Asumsi!$B$26,"HOLD",IF(S12>=Asumsi!$B$27,"FIX","CUT")))))))) -> SCALE
A13: Unboxing Hemat v1 (tes baru) | B13: Non-Spark | C13: TEST | D13: 600000 | E13: 95000 | F13: 26600 | G13: 11000 | H13: 760 | I13: 3 | J13: 450000 | L13: =IF(D13="","",IFERROR(D13/E13*1000,"")) -> 6315.7895 | M13: =IF(D13="","",IF(F13="","",IFERROR(F13/E13,""))) -> 0.28 | N13: =IF(D13="","",IF(G13="","",IFERROR(G13/F13,""))) -> 0.41353383 | O13: =IF(D13="","",IFERROR(H13/E13,"")) -> 0.008 | P13: =IF(D13="","",IFERROR(I13/H13,"")) -> 0.0039473684 | Q13: =IF(D13="","",IFERROR(D13/I13,"")) -> 200000 | R13: =IF(D13="","",IFERROR(J13/D13,"")) -> 0.75 | S13: =IF(D13="","",IFERROR(R13*Asumsi!$B$11,"")) -> 0.3525 | T13: =IF(D13="","",IF(I13<Asumsi!$B$20,"LOW DATA",IF(AND(ISNUMBER(K13),ISNUMBER(O13),N(K13)>0,O13/N(K13)<Asumsi!$B$25),"FATIGUE",IF(AND(ISNUMBER(M13),M13>=Asumsi!$B$22,ISNUMBER(O13),O13<Asumsi!$B$23),"FIX CTA/BODY",IF(AND(ISNUMBER(M13),M13<Asumsi!$B$22,S13<Asumsi!$B$16),"FIX HOOK",IF(S13>=Asumsi!$B$16,"SCALE",IF(S13>=Asumsi!$B$26,"HOLD",IF(S13>=Asumsi!$B$27,"FIX","CUT")))))))) -> LOW DATA
L14: =IF(D14="","",IFERROR(D14/E14*1000,"")) | M14: =IF(D14="","",IF(F14="","",IFERROR(F14/E14,""))) | N14: =IF(D14="","",IF(G14="","",IFERROR(G14/F14,""))) | O14: =IF(D14="","",IFERROR(H14/E14,"")) | P14: =IF(D14="","",IFERROR(I14/H14,"")) | Q14: =IF(D14="","",IFERROR(D14/I14,"")) | R14: =IF(D14="","",IFERROR(J14/D14,"")) | S14: =IF(D14="","",IFERROR(R14*Asumsi!$B$11,"")) | T14: =IF(D14="","",IF(I14<Asumsi!$B$20,"LOW DATA",IF(AND(ISNUMBER(K14),ISNUMBER(O14),N(K14)>0,O14/N(K14)<Asumsi!$B$25),"FATIGUE",IF(AND(ISNUMBER(M14),M14>=Asumsi!$B$22,ISNUMBER(O14),O14<Asumsi!$B$23),"FIX CTA/BODY",IF(AND(ISNUMBER(M14),M14<Asumsi!$B$22,S14<Asumsi!$B$16),"FIX HOOK",IF(S14>=Asumsi!$B$16,"SCALE",IF(S14>=Asumsi!$B$26,"HOLD",IF(S14>=Asumsi!$B$27,"FIX","CUT"))))))))
L15: =IF(D15="","",IFERROR(D15/E15*1000,"")) | M15: =IF(D15="","",IF(F15="","",IFERROR(F15/E15,""))) | N15: =IF(D15="","",IF(G15="","",IFERROR(G15/F15,""))) | O15: =IF(D15="","",IFERROR(H15/E15,"")) | P15: =IF(D15="","",IFERROR(I15/H15,"")) | Q15: =IF(D15="","",IFERROR(D15/I15,"")) | R15: =IF(D15="","",IFERROR(J15/D15,"")) | S15: =IF(D15="","",IFERROR(R15*Asumsi!$B$11,"")) | T15: =IF(D15="","",IF(I15<Asumsi!$B$20,"LOW DATA",IF(AND(ISNUMBER(K15),ISNUMBER(O15),N(K15)>0,O15/N(K15)<Asumsi!$B$25),"FATIGUE",IF(AND(ISNUMBER(M15),M15>=Asumsi!$B$22,ISNUMBER(O15),O15<Asumsi!$B$23),"FIX CTA/BODY",IF(AND(ISNUMBER(M15),M15<Asumsi!$B$22,S15<Asumsi!$B$16),"FIX HOOK",IF(S15>=Asumsi!$B$16,"SCALE",IF(S15>=Asumsi!$B$26,"HOLD",IF(S15>=Asumsi!$B$27,"FIX","CUT"))))))))
L16: =IF(D16="","",IFERROR(D16/E16*1000,"")) | M16: =IF(D16="","",IF(F16="","",IFERROR(F16/E16,""))) | N16: =IF(D16="","",IF(G16="","",IFERROR(G16/F16,""))) | O16: =IF(D16="","",IFERROR(H16/E16,"")) | P16: =IF(D16="","",IFERROR(I16/H16,"")) | Q16: =IF(D16="","",IFERROR(D16/I16,"")) | R16: =IF(D16="","",IFERROR(J16/D16,"")) | S16: =IF(D16="","",IFERROR(R16*Asumsi!$B$11,"")) | T16: =IF(D16="","",IF(I16<Asumsi!$B$20,"LOW DATA",IF(AND(ISNUMBER(K16),ISNUMBER(O16),N(K16)>0,O16/N(K16)<Asumsi!$B$25),"FATIGUE",IF(AND(ISNUMBER(M16),M16>=Asumsi!$B$22,ISNUMBER(O16),O16<Asumsi!$B$23),"FIX CTA/BODY",IF(AND(ISNUMBER(M16),M16<Asumsi!$B$22,S16<Asumsi!$B$16),"FIX HOOK",IF(S16>=Asumsi!$B$16,"SCALE",IF(S16>=Asumsi!$B$26,"HOLD",IF(S16>=Asumsi!$B$27,"FIX","CUT"))))))))
L17: =IF(D17="","",IFERROR(D17/E17*1000,"")) | M17: =IF(D17="","",IF(F17="","",IFERROR(F17/E17,""))) | N17: =IF(D17="","",IF(G17="","",IFERROR(G17/F17,""))) | O17: =IF(D17="","",IFERROR(H17/E17,"")) | P17: =IF(D17="","",IFERROR(I17/H17,"")) | Q17: =IF(D17="","",IFERROR(D17/I17,"")) | R17: =IF(D17="","",IFERROR(J17/D17,"")) | S17: =IF(D17="","",IFERROR(R17*Asumsi!$B$11,"")) | T17: =IF(D17="","",IF(I17<Asumsi!$B$20,"LOW DATA",IF(AND(ISNUMBER(K17),ISNUMBER(O17),N(K17)>0,O17/N(K17)<Asumsi!$B$25),"FATIGUE",IF(AND(ISNUMBER(M17),M17>=Asumsi!$B$22,ISNUMBER(O17),O17<Asumsi!$B$23),"FIX CTA/BODY",IF(AND(ISNUMBER(M17),M17<Asumsi!$B$22,S17<Asumsi!$B$16),"FIX HOOK",IF(S17>=Asumsi!$B$16,"SCALE",IF(S17>=Asumsi!$B$26,"HOLD",IF(S17>=Asumsi!$B$27,"FIX","CUT"))))))))
L18: =IF(D18="","",IFERROR(D18/E18*1000,"")) | M18: =IF(D18="","",IF(F18="","",IFERROR(F18/E18,""))) | N18: =IF(D18="","",IF(G18="","",IFERROR(G18/F18,""))) | O18: =IF(D18="","",IFERROR(H18/E18,"")) | P18: =IF(D18="","",IFERROR(I18/H18,"")) | Q18: =IF(D18="","",IFERROR(D18/I18,"")) | R18: =IF(D18="","",IFERROR(J18/D18,"")) | S18: =IF(D18="","",IFERROR(R18*Asumsi!$B$11,"")) | T18: =IF(D18="","",IF(I18<Asumsi!$B$20,"LOW DATA",IF(AND(ISNUMBER(K18),ISNUMBER(O18),N(K18)>0,O18/N(K18)<Asumsi!$B$25),"FATIGUE",IF(AND(ISNUMBER(M18),M18>=Asumsi!$B$22,ISNUMBER(O18),O18<Asumsi!$B$23),"FIX CTA/BODY",IF(AND(ISNUMBER(M18),M18<Asumsi!$B$22,S18<Asumsi!$B$16),"FIX HOOK",IF(S18>=Asumsi!$B$16,"SCALE",IF(S18>=Asumsi!$B$26,"HOLD",IF(S18>=Asumsi!$B$27,"FIX","CUT"))))))))
L19: =IF(D19="","",IFERROR(D19/E19*1000,"")) | M19: =IF(D19="","",IF(F19="","",IFERROR(F19/E19,""))) | N19: =IF(D19="","",IF(G19="","",IFERROR(G19/F19,""))) | O19: =IF(D19="","",IFERROR(H19/E19,"")) | P19: =IF(D19="","",IFERROR(I19/H19,"")) | Q19: =IF(D19="","",IFERROR(D19/I19,"")) | R19: =IF(D19="","",IFERROR(J19/D19,"")) | S19: =IF(D19="","",IFERROR(R19*Asumsi!$B$11,"")) | T19: =IF(D19="","",IF(I19<Asumsi!$B$20,"LOW DATA",IF(AND(ISNUMBER(K19),ISNUMBER(O19),N(K19)>0,O19/N(K19)<Asumsi!$B$25),"FATIGUE",IF(AND(ISNUMBER(M19),M19>=Asumsi!$B$22,ISNUMBER(O19),O19<Asumsi!$B$23),"FIX CTA/BODY",IF(AND(ISNUMBER(M19),M19<Asumsi!$B$22,S19<Asumsi!$B$16),"FIX HOOK",IF(S19>=Asumsi!$B$16,"SCALE",IF(S19>=Asumsi!$B$26,"HOLD",IF(S19>=Asumsi!$B$27,"FIX","CUT"))))))))
L20: =IF(D20="","",IFERROR(D20/E20*1000,"")) | M20: =IF(D20="","",IF(F20="","",IFERROR(F20/E20,""))) | N20: =IF(D20="","",IF(G20="","",IFERROR(G20/F20,""))) | O20: =IF(D20="","",IFERROR(H20/E20,"")) | P20: =IF(D20="","",IFERROR(I20/H20,"")) | Q20: =IF(D20="","",IFERROR(D20/I20,"")) | R20: =IF(D20="","",IFERROR(J20/D20,"")) | S20: =IF(D20="","",IFERROR(R20*Asumsi!$B$11,"")) | T20: =IF(D20="","",IF(I20<Asumsi!$B$20,"LOW DATA",IF(AND(ISNUMBER(K20),ISNUMBER(O20),N(K20)>0,O20/N(K20)<Asumsi!$B$25),"FATIGUE",IF(AND(ISNUMBER(M20),M20>=Asumsi!$B$22,ISNUMBER(O20),O20<Asumsi!$B$23),"FIX CTA/BODY",IF(AND(ISNUMBER(M20),M20<Asumsi!$B$22,S20<Asumsi!$B$16),"FIX HOOK",IF(S20>=Asumsi!$B$16,"SCALE",IF(S20>=Asumsi!$B$26,"HOLD",IF(S20>=Asumsi!$B$27,"FIX","CUT"))))))))
L21: =IF(D21="","",IFERROR(D21/E21*1000,"")) | M21: =IF(D21="","",IF(F21="","",IFERROR(F21/E21,""))) | N21: =IF(D21="","",IF(G21="","",IFERROR(G21/F21,""))) | O21: =IF(D21="","",IFERROR(H21/E21,"")) | P21: =IF(D21="","",IFERROR(I21/H21,"")) | Q21: =IF(D21="","",IFERROR(D21/I21,"")) | R21: =IF(D21="","",IFERROR(J21/D21,"")) | S21: =IF(D21="","",IFERROR(R21*Asumsi!$B$11,"")) | T21: =IF(D21="","",IF(I21<Asumsi!$B$20,"LOW DATA",IF(AND(ISNUMBER(K21),ISNUMBER(O21),N(K21)>0,O21/N(K21)<Asumsi!$B$25),"FATIGUE",IF(AND(ISNUMBER(M21),M21>=Asumsi!$B$22,ISNUMBER(O21),O21<Asumsi!$B$23),"FIX CTA/BODY",IF(AND(ISNUMBER(M21),M21<Asumsi!$B$22,S21<Asumsi!$B$16),"FIX HOOK",IF(S21>=Asumsi!$B$16,"SCALE",IF(S21>=Asumsi!$B$26,"HOLD",IF(S21>=Asumsi!$B$27,"FIX","CUT"))))))))
L22: =IF(D22="","",IFERROR(D22/E22*1000,"")) | M22: =IF(D22="","",IF(F22="","",IFERROR(F22/E22,""))) | N22: =IF(D22="","",IF(G22="","",IFERROR(G22/F22,""))) | O22: =IF(D22="","",IFERROR(H22/E22,"")) | P22: =IF(D22="","",IFERROR(I22/H22,"")) | Q22: =IF(D22="","",IFERROR(D22/I22,"")) | R22: =IF(D22="","",IFERROR(J22/D22,"")) | S22: =IF(D22="","",IFERROR(R22*Asumsi!$B$11,"")) | T22: =IF(D22="","",IF(I22<Asumsi!$B$20,"LOW DATA",IF(AND(ISNUMBER(K22),ISNUMBER(O22),N(K22)>0,O22/N(K22)<Asumsi!$B$25),"FATIGUE",IF(AND(ISNUMBER(M22),M22>=Asumsi!$B$22,ISNUMBER(O22),O22<Asumsi!$B$23),"FIX CTA/BODY",IF(AND(ISNUMBER(M22),M22<Asumsi!$B$22,S22<Asumsi!$B$16),"FIX HOOK",IF(S22>=Asumsi!$B$16,"SCALE",IF(S22>=Asumsi!$B$26,"HOLD",IF(S22>=Asumsi!$B$27,"FIX","CUT"))))))))
L23: =IF(D23="","",IFERROR(D23/E23*1000,"")) | M23: =IF(D23="","",IF(F23="","",IFERROR(F23/E23,""))) | N23: =IF(D23="","",IF(G23="","",IFERROR(G23/F23,""))) | O23: =IF(D23="","",IFERROR(H23/E23,"")) | P23: =IF(D23="","",IFERROR(I23/H23,"")) | Q23: =IF(D23="","",IFERROR(D23/I23,"")) | R23: =IF(D23="","",IFERROR(J23/D23,"")) | S23: =IF(D23="","",IFERROR(R23*Asumsi!$B$11,"")) | T23: =IF(D23="","",IF(I23<Asumsi!$B$20,"LOW DATA",IF(AND(ISNUMBER(K23),ISNUMBER(O23),N(K23)>0,O23/N(K23)<Asumsi!$B$25),"FATIGUE",IF(AND(ISNUMBER(M23),M23>=Asumsi!$B$22,ISNUMBER(O23),O23<Asumsi!$B$23),"FIX CTA/BODY",IF(AND(ISNUMBER(M23),M23<Asumsi!$B$22,S23<Asumsi!$B$16),"FIX HOOK",IF(S23>=Asumsi!$B$16,"SCALE",IF(S23>=Asumsi!$B$26,"HOLD",IF(S23>=Asumsi!$B$27,"FIX","CUT"))))))))
L24: =IF(D24="","",IFERROR(D24/E24*1000,"")) | M24: =IF(D24="","",IF(F24="","",IFERROR(F24/E24,""))) | N24: =IF(D24="","",IF(G24="","",IFERROR(G24/F24,""))) | O24: =IF(D24="","",IFERROR(H24/E24,"")) | P24: =IF(D24="","",IFERROR(I24/H24,"")) | Q24: =IF(D24="","",IFERROR(D24/I24,"")) | R24: =IF(D24="","",IFERROR(J24/D24,"")) | S24: =IF(D24="","",IFERROR(R24*Asumsi!$B$11,"")) | T24: =IF(D24="","",IF(I24<Asumsi!$B$20,"LOW DATA",IF(AND(ISNUMBER(K24),ISNUMBER(O24),N(K24)>0,O24/N(K24)<Asumsi!$B$25),"FATIGUE",IF(AND(ISNUMBER(M24),M24>=Asumsi!$B$22,ISNUMBER(O24),O24<Asumsi!$B$23),"FIX CTA/BODY",IF(AND(ISNUMBER(M24),M24<Asumsi!$B$22,S24<Asumsi!$B$16),"FIX HOOK",IF(S24>=Asumsi!$B$16,"SCALE",IF(S24>=Asumsi!$B$26,"HOLD",IF(S24>=Asumsi!$B$27,"FIX","CUT"))))))))
L25: =IF(D25="","",IFERROR(D25/E25*1000,"")) | M25: =IF(D25="","",IF(F25="","",IFERROR(F25/E25,""))) | N25: =IF(D25="","",IF(G25="","",IFERROR(G25/F25,""))) | O25: =IF(D25="","",IFERROR(H25/E25,"")) | P25: =IF(D25="","",IFERROR(I25/H25,"")) | Q25: =IF(D25="","",IFERROR(D25/I25,"")) | R25: =IF(D25="","",IFERROR(J25/D25,"")) | S25: =IF(D25="","",IFERROR(R25*Asumsi!$B$11,"")) | T25: =IF(D25="","",IF(I25<Asumsi!$B$20,"LOW DATA",IF(AND(ISNUMBER(K25),ISNUMBER(O25),N(K25)>0,O25/N(K25)<Asumsi!$B$25),"FATIGUE",IF(AND(ISNUMBER(M25),M25>=Asumsi!$B$22,ISNUMBER(O25),O25<Asumsi!$B$23),"FIX CTA/BODY",IF(AND(ISNUMBER(M25),M25<Asumsi!$B$22,S25<Asumsi!$B$16),"FIX HOOK",IF(S25>=Asumsi!$B$16,"SCALE",IF(S25>=Asumsi!$B$26,"HOLD",IF(S25>=Asumsi!$B$27,"FIX","CUT"))))))))
... L36: =IF(D36="","",IFERROR(D36/E36*1000,"")) | M36: =IF(D36="","",IF(F36="","",IFERROR(F36/E36,""))) | N36: =IF(D36="","",IF(G36="","",IFERROR(G36/F36,""))) | O36: =IF(D36="","",IFERROR(H36/E36,"")) | P36: =IF(D36="","",IFERROR(I36/H36,"")) | Q36: =IF(D36="","",IFERROR(D36/I36,"")) | R36: =IF(D36="","",IFERROR(J36/D36,"")) | S36: =IF(D36="","",IFERROR(R36*Asumsi!$B$11,"")) | T36: =IF(D36="","",IF(I36<Asumsi!$B$20,"LOW DATA",IF(AND(ISNUMBER(K36),ISNUMBER(O36),N(K36)>0,O36/N(K36)<Asumsi!$B$25),"FATIGUE",IF(AND(ISNUMBER(M36),M36>=Asumsi!$B$22,ISNUMBER(O36),O36<Asumsi!$B$23),"FIX CTA/BODY",IF(AND(ISNUMBER(M36),M36<Asumsi!$B$22,S36<Asumsi!$B$16),"FIX HOOK",IF(S36>=Asumsi!$B$16,"SCALE",IF(S36>=Asumsi!$B$26,"HOLD",IF(S36>=Asumsi!$B$27,"FIX","CUT"))))))))
A38: Cara baca: FATIGUE = CTR sekarang jatuh di bawah rasio batas dari CTR minggu lalu. FIX CTA/BODY = hook kuat tapi klik sedikit. FIX HOOK = 2 detik pertama lemah.

Sheet LinkedIn Ads
A1: LinkedIn Ads: B2B seragam korporat
A2: September 2026, data FIKTIF. Hasil dilihat sampai SQL dan deal, bukan hanya lead. Won = deal yang sudah closing di periode ini (siklus B2B panjang).
A5: TOTAL / RASIO | D5: =SUM(D7:D36) -> 81000000 | E5: =SUM(E7:E36) -> 840000 | F5: =SUM(F7:F36) -> 6500 | G5: =SUM(G7:G36) -> 209 | H5: =SUM(H7:H36) -> 39 | I5: =SUM(I7:I36) -> 19 | J5: =SUM(J7:J36) -> 6 | K5: =SUM(K7:K36) -> 260000000 | L5: =IFERROR(F5/E5,"") -> 0.0077380952 | M5: =IFERROR(D5/F5,"") -> 12461.538 | N5: =IFERROR(D5/G5,"") -> 387559.81 | O5: =IFERROR(H5/G5,"") -> 0.18660287 | P5: =IFERROR(D5/H5,"") -> 2076923.1 | Q5: =IFERROR(D5/I5,"") -> 4263157.9 | R5: =IFERROR(K5/D5,"") -> 3.2098765 | S5: =IFERROR(K5*Asumsi!$B$31/D5,"") -> 0.96296296
A6: Campaign | B6: Audiens | C6: Format | D6: Biaya (Rp) | E6: Impresi | F6: Klik | G6: Lead | H6: SQL | I6: Peluang (Opp) | J6: Deal Won | K6: Omzet Won (Rp) | L6: CTR | M6: CPC (Rp) | N6: Biaya/Lead (Rp) | O6: Lead ke SQL | P6: Biaya/SQL (Rp) | Q6: Biaya/Opp (Rp) | R6: ROAS Won | S6: POAS Won | T6: Verdict
A7: Lead Gen Form: Panduan Pengadaan Seragam | B7: Manajer Pengadaan, 200-5000 karyawan | C7: Lead Gen Form | D7: 25000000 | E7: 210000 | F7: 1100 | G7: 96 | H7: 8 | I7: 4 | J7: 1 | K7: 45000000 | L7: =IF(D7="","",IFERROR(F7/E7,"")) -> 0.0052380952 | M7: =IF(D7="","",IFERROR(D7/F7,"")) -> 22727.273 | N7: =IF(D7="","",IFERROR(D7/G7,"")) -> 260416.67 | O7: =IF(D7="","",IFERROR(H7/G7,"")) -> 0.083333333 | P7: =IF(D7="","",IFERROR(D7/H7,"")) -> 3125000 | Q7: =IF(D7="","",IFERROR(D7/I7,"")) -> 6250000 | R7: =IF(D7="","",IFERROR(K7/D7,"")) -> 1.8 | S7: =IF(D7="","",IFERROR(K7*Asumsi!$B$31/D7,"")) -> 0.54 | T7: =IF(D7="","",IF(H7<Asumsi!$B$37,"LOW DATA",IF(P7<=Asumsi!$B$36,"SCALE",IF(P7<=1.5*Asumsi!$B$36,"HOLD","CUT")))) -> CUT
A8: Landing Page: Demo Katalog HR | B8: Kepala HR, manufaktur dan retail | C8: Single Image | D8: 20000000 | E8: 150000 | F8: 700 | G8: 24 | H8: 9 | I8: 5 | J8: 2 | K8: 90000000 | L8: =IF(D8="","",IFERROR(F8/E8,"")) -> 0.0046666667 | M8: =IF(D8="","",IFERROR(D8/F8,"")) -> 28571.429 | N8: =IF(D8="","",IFERROR(D8/G8,"")) -> 833333.33 | O8: =IF(D8="","",IFERROR(H8/G8,"")) -> 0.375 | P8: =IF(D8="","",IFERROR(D8/H8,"")) -> 2222222.2 | Q8: =IF(D8="","",IFERROR(D8/I8,"")) -> 4000000 | R8: =IF(D8="","",IFERROR(K8/D8,"")) -> 4.5 | S8: =IF(D8="","",IFERROR(K8*Asumsi!$B$31/D8,"")) -> 1.35 | T8: =IF(D8="","",IF(H8<Asumsi!$B$37,"LOW DATA",IF(P8<=Asumsi!$B$36,"SCALE",IF(P8<=1.5*Asumsi!$B$36,"HOLD","CUT")))) -> HOLD
A9: Thought Leader Ad: Founder | B9: Direktur dan HR Head | C9: Thought Leader Ad | D9: 12000000 | E9: 260000 | F9: 3100 | G9: 18 | H9: 7 | I9: 4 | J9: 1 | K9: 40000000 | L9: =IF(D9="","",IFERROR(F9/E9,"")) -> 0.011923077 | M9: =IF(D9="","",IFERROR(D9/F9,"")) -> 3870.9677 | N9: =IF(D9="","",IFERROR(D9/G9,"")) -> 666666.67 | O9: =IF(D9="","",IFERROR(H9/G9,"")) -> 0.38888889 | P9: =IF(D9="","",IFERROR(D9/H9,"")) -> 1714285.7 | Q9: =IF(D9="","",IFERROR(D9/I9,"")) -> 3000000 | R9: =IF(D9="","",IFERROR(K9/D9,"")) -> 3.3333333 | S9: =IF(D9="","",IFERROR(K9*Asumsi!$B$31/D9,"")) -> 1 | T9: =IF(D9="","",IF(H9<Asumsi!$B$37,"LOW DATA",IF(P9<=Asumsi!$B$36,"SCALE",IF(P9<=1.5*Asumsi!$B$36,"HOLD","CUT")))) -> HOLD
A10: Document Ad: Katalog PDF | B10: Manajer Pengadaan | C10: Document Ad | D10: 10000000 | E10: 120000 | F10: 800 | G10: 40 | H10: 3 | I10: 0 | J10: 0 | K10: 0 | L10: =IF(D10="","",IFERROR(F10/E10,"")) -> 0.0066666667 | M10: =IF(D10="","",IFERROR(D10/F10,"")) -> 12500 | N10: =IF(D10="","",IFERROR(D10/G10,"")) -> 250000 | O10: =IF(D10="","",IFERROR(H10/G10,"")) -> 0.075 | P10: =IF(D10="","",IFERROR(D10/H10,"")) -> 3333333.3 | Q10: =IF(D10="","",IFERROR(D10/I10,"")) | R10: =IF(D10="","",IFERROR(K10/D10,"")) -> 0 | S10: =IF(D10="","",IFERROR(K10*Asumsi!$B$31/D10,"")) -> 0 | T10: =IF(D10="","",IF(H10<Asumsi!$B$37,"LOW DATA",IF(P10<=Asumsi!$B$36,"SCALE",IF(P10<=1.5*Asumsi!$B$36,"HOLD","CUT")))) -> CUT
A11: Retargeting Pengunjung Website | B11: Matched Audience 30 hari | C11: Single Image | D11: 6000000 | E11: 60000 | F11: 540 | G11: 22 | H11: 8 | I11: 4 | J11: 2 | K11: 85000000 | L11: =IF(D11="","",IFERROR(F11/E11,"")) -> 0.009 | M11: =IF(D11="","",IFERROR(D11/F11,"")) -> 11111.111 | N11: =IF(D11="","",IFERROR(D11/G11,"")) -> 272727.27 | O11: =IF(D11="","",IFERROR(H11/G11,"")) -> 0.36363636 | P11: =IF(D11="","",IFERROR(D11/H11,"")) -> 750000 | Q11: =IF(D11="","",IFERROR(D11/I11,"")) -> 1500000 | R11: =IF(D11="","",IFERROR(K11/D11,"")) -> 14.166667 | S11: =IF(D11="","",IFERROR(K11*Asumsi!$B$31/D11,"")) -> 4.25 | T11: =IF(D11="","",IF(H11<Asumsi!$B$37,"LOW DATA",IF(P11<=Asumsi!$B$36,"SCALE",IF(P11<=1.5*Asumsi!$B$36,"HOLD","CUT")))) -> SCALE
A12: ABM Akun Target | B12: Daftar 120 perusahaan | C12: Single Image | D12: 8000000 | E12: 40000 | F12: 260 | G12: 9 | H12: 4 | I12: 2 | J12: 0 | K12: 0 | L12: =IF(D12="","",IFERROR(F12/E12,"")) -> 0.0065 | M12: =IF(D12="","",IFERROR(D12/F12,"")) -> 30769.231 | N12: =IF(D12="","",IFERROR(D12/G12,"")) -> 888888.89 | O12: =IF(D12="","",IFERROR(H12/G12,"")) -> 0.44444444 | P12: =IF(D12="","",IFERROR(D12/H12,"")) -> 2000000 | Q12: =IF(D12="","",IFERROR(D12/I12,"")) -> 4000000 | R12: =IF(D12="","",IFERROR(K12/D12,"")) -> 0 | S12: =IF(D12="","",IFERROR(K12*Asumsi!$B$31/D12,"")) -> 0 | T12: =IF(D12="","",IF(H12<Asumsi!$B$37,"LOW DATA",IF(P12<=Asumsi!$B$36,"SCALE",IF(P12<=1.5*Asumsi!$B$36,"HOLD","CUT")))) -> HOLD
L13: =IF(D13="","",IFERROR(F13/E13,"")) | M13: =IF(D13="","",IFERROR(D13/F13,"")) | N13: =IF(D13="","",IFERROR(D13/G13,"")) | O13: =IF(D13="","",IFERROR(H13/G13,"")) | P13: =IF(D13="","",IFERROR(D13/H13,"")) | Q13: =IF(D13="","",IFERROR(D13/I13,"")) | R13: =IF(D13="","",IFERROR(K13/D13,"")) | S13: =IF(D13="","",IFERROR(K13*Asumsi!$B$31/D13,"")) | T13: =IF(D13="","",IF(H13<Asumsi!$B$37,"LOW DATA",IF(P13<=Asumsi!$B$36,"SCALE",IF(P13<=1.5*Asumsi!$B$36,"HOLD","CUT"))))
L14: =IF(D14="","",IFERROR(F14/E14,"")) | M14: =IF(D14="","",IFERROR(D14/F14,"")) | N14: =IF(D14="","",IFERROR(D14/G14,"")) | O14: =IF(D14="","",IFERROR(H14/G14,"")) | P14: =IF(D14="","",IFERROR(D14/H14,"")) | Q14: =IF(D14="","",IFERROR(D14/I14,"")) | R14: =IF(D14="","",IFERROR(K14/D14,"")) | S14: =IF(D14="","",IFERROR(K14*Asumsi!$B$31/D14,"")) | T14: =IF(D14="","",IF(H14<Asumsi!$B$37,"LOW DATA",IF(P14<=Asumsi!$B$36,"SCALE",IF(P14<=1.5*Asumsi!$B$36,"HOLD","CUT"))))
L15: =IF(D15="","",IFERROR(F15/E15,"")) | M15: =IF(D15="","",IFERROR(D15/F15,"")) | N15: =IF(D15="","",IFERROR(D15/G15,"")) | O15: =IF(D15="","",IFERROR(H15/G15,"")) | P15: =IF(D15="","",IFERROR(D15/H15,"")) | Q15: =IF(D15="","",IFERROR(D15/I15,"")) | R15: =IF(D15="","",IFERROR(K15/D15,"")) | S15: =IF(D15="","",IFERROR(K15*Asumsi!$B$31/D15,"")) | T15: =IF(D15="","",IF(H15<Asumsi!$B$37,"LOW DATA",IF(P15<=Asumsi!$B$36,"SCALE",IF(P15<=1.5*Asumsi!$B$36,"HOLD","CUT"))))
L16: =IF(D16="","",IFERROR(F16/E16,"")) | M16: =IF(D16="","",IFERROR(D16/F16,"")) | N16: =IF(D16="","",IFERROR(D16/G16,"")) | O16: =IF(D16="","",IFERROR(H16/G16,"")) | P16: =IF(D16="","",IFERROR(D16/H16,"")) | Q16: =IF(D16="","",IFERROR(D16/I16,"")) | R16: =IF(D16="","",IFERROR(K16/D16,"")) | S16: =IF(D16="","",IFERROR(K16*Asumsi!$B$31/D16,"")) | T16: =IF(D16="","",IF(H16<Asumsi!$B$37,"LOW DATA",IF(P16<=Asumsi!$B$36,"SCALE",IF(P16<=1.5*Asumsi!$B$36,"HOLD","CUT"))))
L17: =IF(D17="","",IFERROR(F17/E17,"")) | M17: =IF(D17="","",IFERROR(D17/F17,"")) | N17: =IF(D17="","",IFERROR(D17/G17,"")) | O17: =IF(D17="","",IFERROR(H17/G17,"")) | P17: =IF(D17="","",IFERROR(D17/H17,"")) | Q17: =IF(D17="","",IFERROR(D17/I17,"")) | R17: =IF(D17="","",IFERROR(K17/D17,"")) | S17: =IF(D17="","",IFERROR(K17*Asumsi!$B$31/D17,"")) | T17: =IF(D17="","",IF(H17<Asumsi!$B$37,"LOW DATA",IF(P17<=Asumsi!$B$36,"SCALE",IF(P17<=1.5*Asumsi!$B$36,"HOLD","CUT"))))
L18: =IF(D18="","",IFERROR(F18/E18,"")) | M18: =IF(D18="","",IFERROR(D18/F18,"")) | N18: =IF(D18="","",IFERROR(D18/G18,"")) | O18: =IF(D18="","",IFERROR(H18/G18,"")) | P18: =IF(D18="","",IFERROR(D18/H18,"")) | Q18: =IF(D18="","",IFERROR(D18/I18,"")) | R18: =IF(D18="","",IFERROR(K18/D18,"")) | S18: =IF(D18="","",IFERROR(K18*Asumsi!$B$31/D18,"")) | T18: =IF(D18="","",IF(H18<Asumsi!$B$37,"LOW DATA",IF(P18<=Asumsi!$B$36,"SCALE",IF(P18<=1.5*Asumsi!$B$36,"HOLD","CUT"))))
L19: =IF(D19="","",IFERROR(F19/E19,"")) | M19: =IF(D19="","",IFERROR(D19/F19,"")) | N19: =IF(D19="","",IFERROR(D19/G19,"")) | O19: =IF(D19="","",IFERROR(H19/G19,"")) | P19: =IF(D19="","",IFERROR(D19/H19,"")) | Q19: =IF(D19="","",IFERROR(D19/I19,"")) | R19: =IF(D19="","",IFERROR(K19/D19,"")) | S19: =IF(D19="","",IFERROR(K19*Asumsi!$B$31/D19,"")) | T19: =IF(D19="","",IF(H19<Asumsi!$B$37,"LOW DATA",IF(P19<=Asumsi!$B$36,"SCALE",IF(P19<=1.5*Asumsi!$B$36,"HOLD","CUT"))))
L20: =IF(D20="","",IFERROR(F20/E20,"")) | M20: =IF(D20="","",IFERROR(D20/F20,"")) | N20: =IF(D20="","",IFERROR(D20/G20,"")) | O20: =IF(D20="","",IFERROR(H20/G20,"")) | P20: =IF(D20="","",IFERROR(D20/H20,"")) | Q20: =IF(D20="","",IFERROR(D20/I20,"")) | R20: =IF(D20="","",IFERROR(K20/D20,"")) | S20: =IF(D20="","",IFERROR(K20*Asumsi!$B$31/D20,"")) | T20: =IF(D20="","",IF(H20<Asumsi!$B$37,"LOW DATA",IF(P20<=Asumsi!$B$36,"SCALE",IF(P20<=1.5*Asumsi!$B$36,"HOLD","CUT"))))
L21: =IF(D21="","",IFERROR(F21/E21,"")) | M21: =IF(D21="","",IFERROR(D21/F21,"")) | N21: =IF(D21="","",IFERROR(D21/G21,"")) | O21: =IF(D21="","",IFERROR(H21/G21,"")) | P21: =IF(D21="","",IFERROR(D21/H21,"")) | Q21: =IF(D21="","",IFERROR(D21/I21,"")) | R21: =IF(D21="","",IFERROR(K21/D21,"")) | S21: =IF(D21="","",IFERROR(K21*Asumsi!$B$31/D21,"")) | T21: =IF(D21="","",IF(H21<Asumsi!$B$37,"LOW DATA",IF(P21<=Asumsi!$B$36,"SCALE",IF(P21<=1.5*Asumsi!$B$36,"HOLD","CUT"))))
L22: =IF(D22="","",IFERROR(F22/E22,"")) | M22: =IF(D22="","",IFERROR(D22/F22,"")) | N22: =IF(D22="","",IFERROR(D22/G22,"")) | O22: =IF(D22="","",IFERROR(H22/G22,"")) | P22: =IF(D22="","",IFERROR(D22/H22,"")) | Q22: =IF(D22="","",IFERROR(D22/I22,"")) | R22: =IF(D22="","",IFERROR(K22/D22,"")) | S22: =IF(D22="","",IFERROR(K22*Asumsi!$B$31/D22,"")) | T22: =IF(D22="","",IF(H22<Asumsi!$B$37,"LOW DATA",IF(P22<=Asumsi!$B$36,"SCALE",IF(P22<=1.5*Asumsi!$B$36,"HOLD","CUT"))))
L23: =IF(D23="","",IFERROR(F23/E23,"")) | M23: =IF(D23="","",IFERROR(D23/F23,"")) | N23: =IF(D23="","",IFERROR(D23/G23,"")) | O23: =IF(D23="","",IFERROR(H23/G23,"")) | P23: =IF(D23="","",IFERROR(D23/H23,"")) | Q23: =IF(D23="","",IFERROR(D23/I23,"")) | R23: =IF(D23="","",IFERROR(K23/D23,"")) | S23: =IF(D23="","",IFERROR(K23*Asumsi!$B$31/D23,"")) | T23: =IF(D23="","",IF(H23<Asumsi!$B$37,"LOW DATA",IF(P23<=Asumsi!$B$36,"SCALE",IF(P23<=1.5*Asumsi!$B$36,"HOLD","CUT"))))
L24: =IF(D24="","",IFERROR(F24/E24,"")) | M24: =IF(D24="","",IFERROR(D24/F24,"")) | N24: =IF(D24="","",IFERROR(D24/G24,"")) | O24: =IF(D24="","",IFERROR(H24/G24,"")) | P24: =IF(D24="","",IFERROR(D24/H24,"")) | Q24: =IF(D24="","",IFERROR(D24/I24,"")) | R24: =IF(D24="","",IFERROR(K24/D24,"")) | S24: =IF(D24="","",IFERROR(K24*Asumsi!$B$31/D24,"")) | T24: =IF(D24="","",IF(H24<Asumsi!$B$37,"LOW DATA",IF(P24<=Asumsi!$B$36,"SCALE",IF(P24<=1.5*Asumsi!$B$36,"HOLD","CUT"))))
... L36: =IF(D36="","",IFERROR(F36/E36,"")) | M36: =IF(D36="","",IFERROR(D36/F36,"")) | N36: =IF(D36="","",IFERROR(D36/G36,"")) | O36: =IF(D36="","",IFERROR(H36/G36,"")) | P36: =IF(D36="","",IFERROR(D36/H36,"")) | Q36: =IF(D36="","",IFERROR(D36/I36,"")) | R36: =IF(D36="","",IFERROR(K36/D36,"")) | S36: =IF(D36="","",IFERROR(K36*Asumsi!$B$31/D36,"")) | T36: =IF(D36="","",IF(H36<Asumsi!$B$37,"LOW DATA",IF(P36<=Asumsi!$B$36,"SCALE",IF(P36<=1.5*Asumsi!$B$36,"HOLD","CUT"))))
A38: Cara baca: SCALE jika biaya per SQL <= batas di Asumsi. HOLD sampai 1,5x batas. CUT di atasnya. Lead murah belum tentu bagus: lihat Lead ke SQL.

Sheet Marketplace
A1: Marketplace Ads: Shopee, Tokopedia, TikTok Shop
A2: September 2026, data FIKTIF. Biaya admin dan fee di sini contoh: cek halaman biaya terbaru di Seller Center. Persen ditulis pecahan (0.08 = 8%).
A5: TOTAL / RASIO | D5: =SUM(D7:D36) -> 470 | E5: =SUM(E7:E36) -> 517 | F5: =SUM(F7:F36) -> 31000000 | G5: =SUM(G7:G36) -> 109000000 | H5: =SUM(H7:H36) -> 4040000 | I5: =SUM(I7:I36) -> 36910 | Q5: =IFERROR(G5/F5,"") -> 3.516129 | R5: =SUM(R7:R36) -> 37445500 | S5: =IFERROR(R5/G5,"") -> 0.3435367 | T5: =IF(R5<=0,"n/a",G5/R5) -> 2.9108972 | U5: =IFERROR(R5/F5,"") -> 1.2079194 | V5: =SUM(V7:V36) -> 6445500 | W5: =IFERROR(I5/H5,"") -> 0.0091361386 | X5: =IFERROR(D5/I5,"") -> 0.012733677
A6: Platform | B6: Produk / Campaign | C6: Jenis iklan | D6: Pesanan | E6: Unit | F6: Biaya iklan (Rp) | G6: Omzet iklan (Rp) | H6: Impresi | I6: Klik | J6: HPP/unit (Rp) | K6: Komisi/ admin (%) | L6: Biaya tetap/ pesanan (Rp) | M6: Voucher toko (%) | N6: Subsidi ongkir/ pesanan (Rp) | O6: Affiliate (%) | P6: Retur (%) | Q6: ROAS | R6: Kontribusi sebelum iklan (Rp) | S6: Margin kontribusi | T6: Break-even ROAS | U6: POAS | V6: Laba setelah iklan (Rp) | W6: CTR | X6: CVR | Y6: Verdict
A7: Shopee | B7: Kaos Premium | C7: GMV Max | D7: 64 | E7: 70 | F7: 4200000 | G7: 16500000 | H7: 520000 | I7: 5400 | J7: 98000 | K7: 0.08 | L7: 1250 | M7: 0.05 | N7: 3000 | O7: 0 | P7: 0.02 | Q7: =IF(F7="","",IFERROR(G7/F7,"")) -> 3.9285714 | R7: =IF(F7="","",G7*(1-N(K7)-N(M7)-N(O7)-N(P7))-(N(L7)+N(N7))*D7-N(J7)*E7) -> 6893000 | S7: =IF(F7="","",IFERROR(R7/G7,"")) -> 0.41775758 | T7: =IF(F7="","",IF(R7<=0,"n/a",G7/R7)) -> 2.3937328 | U7: =IF(F7="","",IFERROR(R7/F7,"")) -> 1.6411905 | V7: =IF(F7="","",R7-F7) -> 2693000 | W7: =IF(F7="","",IFERROR(I7/H7,"")) -> 0.010384615 | X7: =IF(F7="","",IFERROR(D7/I7,"")) -> 0.011851852 | Y7: =IF(F7="","",IF(D7<Asumsi!$B$41,"LOW DATA",IF(U7>=Asumsi!$B$40,"SCALE",IF(U7>=Asumsi!$B$26,"HOLD",IF(U7>=Asumsi!$B$27,"FIX","CUT"))))) -> SCALE
A8: Shopee | B8: Kaos Polos 3 Pack | C8: Iklan Pencarian | D8: 140 | E8: 160 | F8: 4200000 | G8: 21000000 | H8: 700000 | I8: 9800 | J8: 100000 | K8: 0.08 | L8: 1250 | M8: 0.05 | N8: 3000 | O8: 0 | P8: 0.03 | Q8: =IF(F8="","",IFERROR(G8/F8,"")) -> 5 | R8: =IF(F8="","",G8*(1-N(K8)-N(M8)-N(O8)-N(P8))-(N(L8)+N(N8))*D8-N(J8)*E8) -> 1045000 | S8: =IF(F8="","",IFERROR(R8/G8,"")) -> 0.049761905 | T8: =IF(F8="","",IF(R8<=0,"n/a",G8/R8)) -> 20.095694 | U8: =IF(F8="","",IFERROR(R8/F8,"")) -> 0.24880952 | V8: =IF(F8="","",R8-F8) -> -3155000 | W8: =IF(F8="","",IFERROR(I8/H8,"")) -> 0.014 | X8: =IF(F8="","",IFERROR(D8/I8,"")) -> 0.014285714 | Y8: =IF(F8="","",IF(D8<Asumsi!$B$41,"LOW DATA",IF(U8>=Asumsi!$B$40,"SCALE",IF(U8>=Asumsi!$B$26,"HOLD",IF(U8>=Asumsi!$B$27,"FIX","CUT"))))) -> CUT
A9: Shopee | B9: Hoodie Oversize | C9: GMV Max | D9: 52 | E9: 58 | F9: 5500000 | G9: 15800000 | H9: 480000 | I9: 4100 | J9: 105000 | K9: 0.08 | L9: 1250 | M9: 0.05 | N9: 3000 | O9: 0 | P9: 0.02 | Q9: =IF(F9="","",IFERROR(G9/F9,"")) -> 2.8727273 | R9: =IF(F9="","",G9*(1-N(K9)-N(M9)-N(O9)-N(P9))-(N(L9)+N(N9))*D9-N(J9)*E9) -> 7119000 | S9: =IF(F9="","",IFERROR(R9/G9,"")) -> 0.45056962 | T9: =IF(F9="","",IF(R9<=0,"n/a",G9/R9)) -> 2.2194128 | U9: =IF(F9="","",IFERROR(R9/F9,"")) -> 1.2943636 | V9: =IF(F9="","",R9-F9) -> 1619000 | W9: =IF(F9="","",IFERROR(I9/H9,"")) -> 0.0085416667 | X9: =IF(F9="","",IFERROR(D9/I9,"")) -> 0.012682927 | Y9: =IF(F9="","",IF(D9<Asumsi!$B$41,"LOW DATA",IF(U9>=Asumsi!$B$40,"SCALE",IF(U9>=Asumsi!$B$26,"HOLD",IF(U9>=Asumsi!$B$27,"FIX","CUT"))))) -> HOLD
A10: Shopee | B10: Tote Bag | C10: Iklan Pencarian | D10: 3 | E10: 3 | F10: 400000 | G10: 900000 | H10: 60000 | I10: 410 | J10: 60000 | K10: 0.08 | L10: 1250 | M10: 0.05 | N10: 3000 | O10: 0 | P10: 0.02 | Q10: =IF(F10="","",IFERROR(G10/F10,"")) -> 2.25 | R10: =IF(F10="","",G10*(1-N(K10)-N(M10)-N(O10)-N(P10))-(N(L10)+N(N10))*D10-N(J10)*E10) -> 572250 | S10: =IF(F10="","",IFERROR(R10/G10,"")) -> 0.63583333 | T10: =IF(F10="","",IF(R10<=0,"n/a",G10/R10)) -> 1.5727392 | U10: =IF(F10="","",IFERROR(R10/F10,"")) -> 1.430625 | V10: =IF(F10="","",R10-F10) -> 172250 | W10: =IF(F10="","",IFERROR(I10/H10,"")) -> 0.0068333333 | X10: =IF(F10="","",IFERROR(D10/I10,"")) -> 0.0073170732 | Y10: =IF(F10="","",IF(D10<Asumsi!$B$41,"LOW DATA",IF(U10>=Asumsi!$B$40,"SCALE",IF(U10>=Asumsi!$B$26,"HOLD",IF(U10>=Asumsi!$B$27,"FIX","CUT"))))) -> LOW DATA
A11: Shopee | B11: Celana Cargo | C11: Iklan Pencarian | D11: 41 | E11: 44 | F11: 3000000 | G11: 10300000 | H11: 250000 | I11: 2900 | J11: 112000 | K11: 0.08 | L11: 1250 | M11: 0.05 | N11: 3000 | O11: 0 | P11: 0.02 | Q11: =IF(F11="","",IFERROR(G11/F11,"")) -> 3.4333333 | R11: =IF(F11="","",G11*(1-N(K11)-N(M11)-N(O11)-N(P11))-(N(L11)+N(N11))*D11-N(J11)*E11) -> 3652750 | S11: =IF(F11="","",IFERROR(R11/G11,"")) -> 0.35463592 | T11: =IF(F11="","",IF(R11<=0,"n/a",G11/R11)) -> 2.8197933 | U11: =IF(F11="","",IFERROR(R11/F11,"")) -> 1.2175833 | V11: =IF(F11="","",R11-F11) -> 652750 | W11: =IF(F11="","",IFERROR(I11/H11,"")) -> 0.0116 | X11: =IF(F11="","",IFERROR(D11/I11,"")) -> 0.014137931 | Y11: =IF(F11="","",IF(D11<Asumsi!$B$41,"LOW DATA",IF(U11>=Asumsi!$B$40,"SCALE",IF(U11>=Asumsi!$B$26,"HOLD",IF(U11>=Asumsi!$B$27,"FIX","CUT"))))) -> HOLD
A12: Tokopedia | B12: Kaos Premium | C12: Iklan Produk | D12: 22 | E12: 24 | F12: 1800000 | G12: 5600000 | H12: 160000 | I12: 1500 | J12: 98000 | K12: 0.07 | L12: 1250 | M12: 0.03 | N12: 2500 | O12: 0 | P12: 0.01 | Q12: =IF(F12="","",IFERROR(G12/F12,"")) -> 3.1111111 | R12: =IF(F12="","",G12*(1-N(K12)-N(M12)-N(O12)-N(P12))-(N(L12)+N(N12))*D12-N(J12)*E12) -> 2549500 | S12: =IF(F12="","",IFERROR(R12/G12,"")) -> 0.45526786 | T12: =IF(F12="","",IF(R12<=0,"n/a",G12/R12)) -> 2.1965091 | U12: =IF(F12="","",IFERROR(R12/F12,"")) -> 1.4163889 | V12: =IF(F12="","",R12-F12) -> 749500 | W12: =IF(F12="","",IFERROR(I12/H12,"")) -> 0.009375 | X12: =IF(F12="","",IFERROR(D12/I12,"")) -> 0.014666667 | Y12: =IF(F12="","",IF(D12<Asumsi!$B$41,"LOW DATA",IF(U12>=Asumsi!$B$40,"SCALE",IF(U12>=Asumsi!$B$26,"HOLD",IF(U12>=Asumsi!$B$27,"FIX","CUT"))))) -> SCALE
A13: Tokopedia | B13: Hoodie Oversize | C13: Iklan Produk | D13: 15 | E13: 16 | F13: 2200000 | G13: 4300000 | H13: 140000 | I13: 1200 | J13: 105000 | K13: 0.07 | L13: 1250 | M13: 0.03 | N13: 2500 | O13: 0 | P13: 0.01 | Q13: =IF(F13="","",IFERROR(G13/F13,"")) -> 1.9545455 | R13: =IF(F13="","",G13*(1-N(K13)-N(M13)-N(O13)-N(P13))-(N(L13)+N(N13))*D13-N(J13)*E13) -> 2090750 | S13: =IF(F13="","",IFERROR(R13/G13,"")) -> 0.48622093 | T13: =IF(F13="","",IF(R13<=0,"n/a",G13/R13)) -> 2.0566782 | U13: =IF(F13="","",IFERROR(R13/F13,"")) -> 0.95034091 | V13: =IF(F13="","",R13-F13) -> -109250 | W13: =IF(F13="","",IFERROR(I13/H13,"")) -> 0.0085714286 | X13: =IF(F13="","",IFERROR(D13/I13,"")) -> 0.0125 | Y13: =IF(F13="","",IF(D13<Asumsi!$B$41,"LOW DATA",IF(U13>=Asumsi!$B$40,"SCALE",IF(U13>=Asumsi!$B$26,"HOLD",IF(U13>=Asumsi!$B$27,"FIX","CUT"))))) -> FIX
A14: TikTok Shop | B14: Hoodie Oversize | C14: GMV Max | D14: 38 | E14: 40 | F14: 3000000 | G14: 13800000 | H14: 610000 | I14: 3900 | J14: 105000 | K14: 0.06 | L14: 1250 | M14: 0.04 | N14: 2500 | O14: 0.1 | P14: 0.03 | Q14: =IF(F14="","",IFERROR(G14/F14,"")) -> 4.6 | R14: =IF(F14="","",G14*(1-N(K14)-N(M14)-N(O14)-N(P14))-(N(L14)+N(N14))*D14-N(J14)*E14) -> 6283500 | S14: =IF(F14="","",IFERROR(R14/G14,"")) -> 0.45532609 | T14: =IF(F14="","",IF(R14<=0,"n/a",G14/R14)) -> 2.1962282 | U14: =IF(F14="","",IFERROR(R14/F14,"")) -> 2.0945 | V14: =IF(F14="","",R14-F14) -> 3283500 | W14: =IF(F14="","",IFERROR(I14/H14,"")) -> 0.0063934426 | X14: =IF(F14="","",IFERROR(D14/I14,"")) -> 0.0097435897 | Y14: =IF(F14="","",IF(D14<Asumsi!$B$41,"LOW DATA",IF(U14>=Asumsi!$B$40,"SCALE",IF(U14>=Asumsi!$B$26,"HOLD",IF(U14>=Asumsi!$B$27,"FIX","CUT"))))) -> SCALE
A15: TikTok Shop | B15: Kaos Premium | C15: GMV Max | D15: 61 | E15: 66 | F15: 4800000 | G15: 15400000 | H15: 820000 | I15: 5600 | J15: 98000 | K15: 0.06 | L15: 1250 | M15: 0.04 | N15: 2500 | O15: 0.1 | P15: 0.02 | Q15: =IF(F15="","",IFERROR(G15/F15,"")) -> 3.2083333 | R15: =IF(F15="","",G15*(1-N(K15)-N(M15)-N(O15)-N(P15))-(N(L15)+N(N15))*D15-N(J15)*E15) -> 5315250 | S15: =IF(F15="","",IFERROR(R15/G15,"")) -> 0.3451461 | T15: =IF(F15="","",IF(R15<=0,"n/a",G15/R15)) -> 2.8973237 | U15: =IF(F15="","",IFERROR(R15/F15,"")) -> 1.1073438 | V15: =IF(F15="","",R15-F15) -> 515250 | W15: =IF(F15="","",IFERROR(I15/H15,"")) -> 0.0068292683 | X15: =IF(F15="","",IFERROR(D15/I15,"")) -> 0.010892857 | Y15: =IF(F15="","",IF(D15<Asumsi!$B$41,"LOW DATA",IF(U15>=Asumsi!$B$40,"SCALE",IF(U15>=Asumsi!$B$26,"HOLD",IF(U15>=Asumsi!$B$27,"FIX","CUT"))))) -> HOLD
A16: TikTok Shop | B16: Tote Bag | C16: GMV Max | D16: 34 | E16: 36 | F16: 1900000 | G16: 5400000 | H16: 300000 | I16: 2100 | J16: 60000 | K16: 0.06 | L16: 1250 | M16: 0.04 | N16: 2500 | O16: 0.1 | P16: 0.02 | Q16: =IF(F16="","",IFERROR(G16/F16,"")) -> 2.8421053 | R16: =IF(F16="","",G16*(1-N(K16)-N(M16)-N(O16)-N(P16))-(N(L16)+N(N16))*D16-N(J16)*E16) -> 1924500 | S16: =IF(F16="","",IFERROR(R16/G16,"")) -> 0.35638889 | T16: =IF(F16="","",IF(R16<=0,"n/a",G16/R16)) -> 2.8059236 | U16: =IF(F16="","",IFERROR(R16/F16,"")) -> 1.0128947 | V16: =IF(F16="","",R16-F16) -> 24500 | W16: =IF(F16="","",IFERROR(I16/H16,"")) -> 0.007 | X16: =IF(F16="","",IFERROR(D16/I16,"")) -> 0.016190476 | Y16: =IF(F16="","",IF(D16<Asumsi!$B$41,"LOW DATA",IF(U16>=Asumsi!$B$40,"SCALE",IF(U16>=Asumsi!$B$26,"HOLD",IF(U16>=Asumsi!$B$27,"FIX","CUT"))))) -> HOLD
Q17: =IF(F17="","",IFERROR(G17/F17,"")) | R17: =IF(F17="","",G17*(1-N(K17)-N(M17)-N(O17)-N(P17))-(N(L17)+N(N17))*D17-N(J17)*E17) | S17: =IF(F17="","",IFERROR(R17/G17,"")) | T17: =IF(F17="","",IF(R17<=0,"n/a",G17/R17)) | U17: =IF(F17="","",IFERROR(R17/F17,"")) | V17: =IF(F17="","",R17-F17) | W17: =IF(F17="","",IFERROR(I17/H17,"")) | X17: =IF(F17="","",IFERROR(D17/I17,"")) | Y17: =IF(F17="","",IF(D17<Asumsi!$B$41,"LOW DATA",IF(U17>=Asumsi!$B$40,"SCALE",IF(U17>=Asumsi!$B$26,"HOLD",IF(U17>=Asumsi!$B$27,"FIX","CUT")))))
Q18: =IF(F18="","",IFERROR(G18/F18,"")) | R18: =IF(F18="","",G18*(1-N(K18)-N(M18)-N(O18)-N(P18))-(N(L18)+N(N18))*D18-N(J18)*E18) | S18: =IF(F18="","",IFERROR(R18/G18,"")) | T18: =IF(F18="","",IF(R18<=0,"n/a",G18/R18)) | U18: =IF(F18="","",IFERROR(R18/F18,"")) | V18: =IF(F18="","",R18-F18) | W18: =IF(F18="","",IFERROR(I18/H18,"")) | X18: =IF(F18="","",IFERROR(D18/I18,"")) | Y18: =IF(F18="","",IF(D18<Asumsi!$B$41,"LOW DATA",IF(U18>=Asumsi!$B$40,"SCALE",IF(U18>=Asumsi!$B$26,"HOLD",IF(U18>=Asumsi!$B$27,"FIX","CUT")))))
Q19: =IF(F19="","",IFERROR(G19/F19,"")) | R19: =IF(F19="","",G19*(1-N(K19)-N(M19)-N(O19)-N(P19))-(N(L19)+N(N19))*D19-N(J19)*E19) | S19: =IF(F19="","",IFERROR(R19/G19,"")) | T19: =IF(F19="","",IF(R19<=0,"n/a",G19/R19)) | U19: =IF(F19="","",IFERROR(R19/F19,"")) | V19: =IF(F19="","",R19-F19) | W19: =IF(F19="","",IFERROR(I19/H19,"")) | X19: =IF(F19="","",IFERROR(D19/I19,"")) | Y19: =IF(F19="","",IF(D19<Asumsi!$B$41,"LOW DATA",IF(U19>=Asumsi!$B$40,"SCALE",IF(U19>=Asumsi!$B$26,"HOLD",IF(U19>=Asumsi!$B$27,"FIX","CUT")))))
Q20: =IF(F20="","",IFERROR(G20/F20,"")) | R20: =IF(F20="","",G20*(1-N(K20)-N(M20)-N(O20)-N(P20))-(N(L20)+N(N20))*D20-N(J20)*E20) | S20: =IF(F20="","",IFERROR(R20/G20,"")) | T20: =IF(F20="","",IF(R20<=0,"n/a",G20/R20)) | U20: =IF(F20="","",IFERROR(R20/F20,"")) | V20: =IF(F20="","",R20-F20) | W20: =IF(F20="","",IFERROR(I20/H20,"")) | X20: =IF(F20="","",IFERROR(D20/I20,"")) | Y20: =IF(F20="","",IF(D20<Asumsi!$B$41,"LOW DATA",IF(U20>=Asumsi!$B$40,"SCALE",IF(U20>=Asumsi!$B$26,"HOLD",IF(U20>=Asumsi!$B$27,"FIX","CUT")))))
Q21: =IF(F21="","",IFERROR(G21/F21,"")) | R21: =IF(F21="","",G21*(1-N(K21)-N(M21)-N(O21)-N(P21))-(N(L21)+N(N21))*D21-N(J21)*E21) | S21: =IF(F21="","",IFERROR(R21/G21,"")) | T21: =IF(F21="","",IF(R21<=0,"n/a",G21/R21)) | U21: =IF(F21="","",IFERROR(R21/F21,"")) | V21: =IF(F21="","",R21-F21) | W21: =IF(F21="","",IFERROR(I21/H21,"")) | X21: =IF(F21="","",IFERROR(D21/I21,"")) | Y21: =IF(F21="","",IF(D21<Asumsi!$B$41,"LOW DATA",IF(U21>=Asumsi!$B$40,"SCALE",IF(U21>=Asumsi!$B$26,"HOLD",IF(U21>=Asumsi!$B$27,"FIX","CUT")))))
Q22: =IF(F22="","",IFERROR(G22/F22,"")) | R22: =IF(F22="","",G22*(1-N(K22)-N(M22)-N(O22)-N(P22))-(N(L22)+N(N22))*D22-N(J22)*E22) | S22: =IF(F22="","",IFERROR(R22/G22,"")) | T22: =IF(F22="","",IF(R22<=0,"n/a",G22/R22)) | U22: =IF(F22="","",IFERROR(R22/F22,"")) | V22: =IF(F22="","",R22-F22) | W22: =IF(F22="","",IFERROR(I22/H22,"")) | X22: =IF(F22="","",IFERROR(D22/I22,"")) | Y22: =IF(F22="","",IF(D22<Asumsi!$B$41,"LOW DATA",IF(U22>=Asumsi!$B$40,"SCALE",IF(U22>=Asumsi!$B$26,"HOLD",IF(U22>=Asumsi!$B$27,"FIX","CUT")))))
Q23: =IF(F23="","",IFERROR(G23/F23,"")) | R23: =IF(F23="","",G23*(1-N(K23)-N(M23)-N(O23)-N(P23))-(N(L23)+N(N23))*D23-N(J23)*E23) | S23: =IF(F23="","",IFERROR(R23/G23,"")) | T23: =IF(F23="","",IF(R23<=0,"n/a",G23/R23)) | U23: =IF(F23="","",IFERROR(R23/F23,"")) | V23: =IF(F23="","",R23-F23) | W23: =IF(F23="","",IFERROR(I23/H23,"")) | X23: =IF(F23="","",IFERROR(D23/I23,"")) | Y23: =IF(F23="","",IF(D23<Asumsi!$B$41,"LOW DATA",IF(U23>=Asumsi!$B$40,"SCALE",IF(U23>=Asumsi!$B$26,"HOLD",IF(U23>=Asumsi!$B$27,"FIX","CUT")))))
Q24: =IF(F24="","",IFERROR(G24/F24,"")) | R24: =IF(F24="","",G24*(1-N(K24)-N(M24)-N(O24)-N(P24))-(N(L24)+N(N24))*D24-N(J24)*E24) | S24: =IF(F24="","",IFERROR(R24/G24,"")) | T24: =IF(F24="","",IF(R24<=0,"n/a",G24/R24)) | U24: =IF(F24="","",IFERROR(R24/F24,"")) | V24: =IF(F24="","",R24-F24) | W24: =IF(F24="","",IFERROR(I24/H24,"")) | X24: =IF(F24="","",IFERROR(D24/I24,"")) | Y24: =IF(F24="","",IF(D24<Asumsi!$B$41,"LOW DATA",IF(U24>=Asumsi!$B$40,"SCALE",IF(U24>=Asumsi!$B$26,"HOLD",IF(U24>=Asumsi!$B$27,"FIX","CUT")))))
Q25: =IF(F25="","",IFERROR(G25/F25,"")) | R25: =IF(F25="","",G25*(1-N(K25)-N(M25)-N(O25)-N(P25))-(N(L25)+N(N25))*D25-N(J25)*E25) | S25: =IF(F25="","",IFERROR(R25/G25,"")) | T25: =IF(F25="","",IF(R25<=0,"n/a",G25/R25)) | U25: =IF(F25="","",IFERROR(R25/F25,"")) | V25: =IF(F25="","",R25-F25) | W25: =IF(F25="","",IFERROR(I25/H25,"")) | X25: =IF(F25="","",IFERROR(D25/I25,"")) | Y25: =IF(F25="","",IF(D25<Asumsi!$B$41,"LOW DATA",IF(U25>=Asumsi!$B$40,"SCALE",IF(U25>=Asumsi!$B$26,"HOLD",IF(U25>=Asumsi!$B$27,"FIX","CUT")))))
Q26: =IF(F26="","",IFERROR(G26/F26,"")) | R26: =IF(F26="","",G26*(1-N(K26)-N(M26)-N(O26)-N(P26))-(N(L26)+N(N26))*D26-N(J26)*E26) | S26: =IF(F26="","",IFERROR(R26/G26,"")) | T26: =IF(F26="","",IF(R26<=0,"n/a",G26/R26)) | U26: =IF(F26="","",IFERROR(R26/F26,"")) | V26: =IF(F26="","",R26-F26) | W26: =IF(F26="","",IFERROR(I26/H26,"")) | X26: =IF(F26="","",IFERROR(D26/I26,"")) | Y26: =IF(F26="","",IF(D26<Asumsi!$B$41,"LOW DATA",IF(U26>=Asumsi!$B$40,"SCALE",IF(U26>=Asumsi!$B$26,"HOLD",IF(U26>=Asumsi!$B$27,"FIX","CUT")))))
Q27: =IF(F27="","",IFERROR(G27/F27,"")) | R27: =IF(F27="","",G27*(1-N(K27)-N(M27)-N(O27)-N(P27))-(N(L27)+N(N27))*D27-N(J27)*E27) | S27: =IF(F27="","",IFERROR(R27/G27,"")) | T27: =IF(F27="","",IF(R27<=0,"n/a",G27/R27)) | U27: =IF(F27="","",IFERROR(R27/F27,"")) | V27: =IF(F27="","",R27-F27) | W27: =IF(F27="","",IFERROR(I27/H27,"")) | X27: =IF(F27="","",IFERROR(D27/I27,"")) | Y27: =IF(F27="","",IF(D27<Asumsi!$B$41,"LOW DATA",IF(U27>=Asumsi!$B$40,"SCALE",IF(U27>=Asumsi!$B$26,"HOLD",IF(U27>=Asumsi!$B$27,"FIX","CUT")))))
Q28: =IF(F28="","",IFERROR(G28/F28,"")) | R28: =IF(F28="","",G28*(1-N(K28)-N(M28)-N(O28)-N(P28))-(N(L28)+N(N28))*D28-N(J28)*E28) | S28: =IF(F28="","",IFERROR(R28/G28,"")) | T28: =IF(F28="","",IF(R28<=0,"n/a",G28/R28)) | U28: =IF(F28="","",IFERROR(R28/F28,"")) | V28: =IF(F28="","",R28-F28) | W28: =IF(F28="","",IFERROR(I28/H28,"")) | X28: =IF(F28="","",IFERROR(D28/I28,"")) | Y28: =IF(F28="","",IF(D28<Asumsi!$B$41,"LOW DATA",IF(U28>=Asumsi!$B$40,"SCALE",IF(U28>=Asumsi!$B$26,"HOLD",IF(U28>=Asumsi!$B$27,"FIX","CUT")))))
... Q36: =IF(F36="","",IFERROR(G36/F36,"")) | R36: =IF(F36="","",G36*(1-N(K36)-N(M36)-N(O36)-N(P36))-(N(L36)+N(N36))*D36-N(J36)*E36) | S36: =IF(F36="","",IFERROR(R36/G36,"")) | T36: =IF(F36="","",IF(R36<=0,"n/a",G36/R36)) | U36: =IF(F36="","",IFERROR(R36/F36,"")) | V36: =IF(F36="","",R36-F36) | W36: =IF(F36="","",IFERROR(I36/H36,"")) | X36: =IF(F36="","",IFERROR(D36/I36,"")) | Y36: =IF(F36="","",IF(D36<Asumsi!$B$41,"LOW DATA",IF(U36>=Asumsi!$B$40,"SCALE",IF(U36>=Asumsi!$B$26,"HOLD",IF(U36>=Asumsi!$B$27,"FIX","CUT")))))
A38: RINGKASAN PER PLATFORM: TACoS dan POAS
A39: Platform | B39: Omzet total toko (Rp) | C39: Biaya iklan (Rp) | D39: Omzet iklan (Rp) | E39: TACoS | F39: Omzet iklan / total | G39: Kontribusi iklan (Rp) | H39: POAS | I39: Laba setelah iklan (Rp)
A40: Shopee | B40: 68000000 | C40: =SUMIFS($F$7:$F$36,$A$7:$A$36,A40) -> 17300000 | D40: =SUMIFS($G$7:$G$36,$A$7:$A$36,A40) -> 64500000 | E40: =IFERROR(C40/B40,"") -> 0.25441176 | F40: =IFERROR(D40/B40,"") -> 0.94852941 | G40: =SUMIFS($R$7:$R$36,$A$7:$A$36,A40) -> 19282000 | H40: =IFERROR(G40/C40,"") -> 1.1145665 | I40: =G40-C40 -> 1982000
A41: Tokopedia | B41: 22000000 | C41: =SUMIFS($F$7:$F$36,$A$7:$A$36,A41) -> 4000000 | D41: =SUMIFS($G$7:$G$36,$A$7:$A$36,A41) -> 9900000 | E41: =IFERROR(C41/B41,"") -> 0.18181818 | F41: =IFERROR(D41/B41,"") -> 0.45 | G41: =SUMIFS($R$7:$R$36,$A$7:$A$36,A41) -> 4640250 | H41: =IFERROR(G41/C41,"") -> 1.1600625 | I41: =G41-C41 -> 640250
A42: TikTok Shop | B42: 41000000 | C42: =SUMIFS($F$7:$F$36,$A$7:$A$36,A42) -> 9700000 | D42: =SUMIFS($G$7:$G$36,$A$7:$A$36,A42) -> 34600000 | E42: =IFERROR(C42/B42,"") -> 0.23658537 | F42: =IFERROR(D42/B42,"") -> 0.84390244 | G42: =SUMIFS($R$7:$R$36,$A$7:$A$36,A42) -> 13523250 | H42: =IFERROR(G42/C42,"") -> 1.3941495 | I42: =G42-C42 -> 3823250
A43: TOTAL | B43: =SUM(B40:B42) -> 131000000 | C43: =SUM(C40:C42) -> 31000000 | D43: =SUM(D40:D42) -> 109000000 | E43: =IFERROR(C43/B43,"") -> 0.23664122 | F43: =IFERROR(D43/B43,"") -> 0.83206107 | G43: =SUM(G40:G42) -> 37445500 | H43: =IFERROR(G43/C43,"") -> 1.2079194 | I43: =SUM(I40:I42) -> 6445500
A45: Catatan: omzet total toko = iklan + organik (data fiktif). Isi dari laporan penjualan Seller Center. Sel biru kolom B.

Sheet Mingguan
A1: Tren Mingguan Lintas Platform: MER dan profit
A2: 8 minggu, data FIKTIF. Omzet bisnis = sumber kebenaran (kas/penjualan), bukan klaim platform.
A6: Minggu | B6: Mulai (Senin) | C6: Google (Rp) | D6: Meta (Rp) | E6: TikTok (Rp) | F6: LinkedIn (Rp) | G6: Iklan marketplace (Rp) | H6: Total biaya iklan (Rp) | I6: Omzet bisnis total (Rp) | J6: Klaim nilai konversi semua platform (Rp) | K6: Pelanggan baru | L6: Margin kontribusi blended | M6: MER | N6: Break-even MER | O6: Klaim platform vs aktual | P6: CAC blended (Rp) | Q6: Kontribusi (Rp) | R6: Laba setelah iklan (Rp) | S6: POAS blended | T6: Status | U6: Catatan
A7: M1 | B7: 46251 | C7: 25000000 | D7: 9500000 | E7: 5000000 | F7: 19000000 | G7: 6500000 | H7: =SUM(C7:G7) -> 65000000 | I7: 188000000 | J7: 232000000 | K7: 880 | L7: 0.42 | M7: =IFERROR(I7/H7,"") -> 2.8923077 | N7: =IFERROR(1/L7,"") -> 2.3809524 | O7: =IFERROR(J7/I7-1,"") -> 0.23404255 | P7: =IFERROR(H7/K7,"") -> 73863.636 | Q7: =I7*L7 -> 78960000 | R7: =Q7-H7 -> 13960000 | S7: =IFERROR(Q7/H7,"") -> 1.2147692 | T7: =IF(S7="","",IF(S7>=Asumsi!$B$16,"SEHAT",IF(S7>=1,"TIPIS","RUGI"))) -> TIPIS
A8: M2 | B8: 46258 | C8: 25500000 | D8: 9800000 | E8: 5500000 | F8: 19000000 | G8: 6800000 | H8: =SUM(C8:G8) -> 66600000 | I8: 192000000 | J8: 240000000 | K8: 900 | L8: 0.42 | M8: =IFERROR(I8/H8,"") -> 2.8828829 | N8: =IFERROR(1/L8,"") -> 2.3809524 | O8: =IFERROR(J8/I8-1,"") -> 0.25 | P8: =IFERROR(H8/K8,"") -> 74000 | Q8: =I8*L8 -> 80640000 | R8: =Q8-H8 -> 14040000 | S8: =IFERROR(Q8/H8,"") -> 1.2108108 | T8: =IF(S8="","",IF(S8>=Asumsi!$B$16,"SEHAT",IF(S8>=1,"TIPIS","RUGI"))) -> TIPIS
A9: M3 | B9: 46265 | C9: 26000000 | D9: 10200000 | E9: 6000000 | F9: 19500000 | G9: 7000000 | H9: =SUM(C9:G9) -> 68700000 | I9: 199000000 | J9: 251000000 | K9: 925 | L9: 0.42 | M9: =IFERROR(I9/H9,"") -> 2.8966521 | N9: =IFERROR(1/L9,"") -> 2.3809524 | O9: =IFERROR(J9/I9-1,"") -> 0.26130653 | P9: =IFERROR(H9/K9,"") -> 74270.27 | Q9: =I9*L9 -> 83580000 | R9: =Q9-H9 -> 14880000 | S9: =IFERROR(Q9/H9,"") -> 1.2165939 | T9: =IF(S9="","",IF(S9>=Asumsi!$B$16,"SEHAT",IF(S9>=1,"TIPIS","RUGI"))) -> TIPIS
A10: M4 | B10: 46272 | C10: 26500000 | D10: 10000000 | E10: 6500000 | F10: 19000000 | G10: 7000000 | H10: =SUM(C10:G10) -> 69000000 | I10: 195000000 | J10: 190000000 | K10: 910 | L10: 0.42 | M10: =IFERROR(I10/H10,"") -> 2.826087 | N10: =IFERROR(1/L10,"") -> 2.3809524 | O10: =IFERROR(J10/I10-1,"") -> -0.025641026 | P10: =IFERROR(H10/K10,"") -> 75824.176 | Q10: =I10*L10 -> 81900000 | R10: =Q10-H10 -> 12900000 | S10: =IFERROR(Q10/H10,"") -> 1.1869565 | T10: =IF(S10="","",IF(S10>=Asumsi!$B$16,"SEHAT",IF(S10>=1,"TIPIS","RUGI"))) -> TIPIS | U10: Tag Google rusak setelah update website: konversi terlapor jatuh, omzet nyata tidak. Lihat kolom klaim vs aktual.
A11: M5 | B11: 46279 | C11: 26500000 | D11: 10500000 | E11: 6500000 | F11: 20000000 | G11: 7200000 | H11: =SUM(C11:G11) -> 70700000 | I11: 207000000 | J11: 262000000 | K11: 950 | L11: 0.42 | M11: =IFERROR(I11/H11,"") -> 2.9278642 | N11: =IFERROR(1/L11,"") -> 2.3809524 | O11: =IFERROR(J11/I11-1,"") -> 0.26570048 | P11: =IFERROR(H11/K11,"") -> 74421.053 | Q11: =I11*L11 -> 86940000 | R11: =Q11-H11 -> 16240000 | S11: =IFERROR(Q11/H11,"") -> 1.229703 | T11: =IF(S11="","",IF(S11>=Asumsi!$B$16,"SEHAT",IF(S11>=1,"TIPIS","RUGI"))) -> TIPIS | U11: Tag diperbaiki.
A12: M6 | B12: 46286 | C12: 27000000 | D12: 11000000 | E12: 7000000 | F12: 20000000 | G12: 7500000 | H12: =SUM(C12:G12) -> 72500000 | I12: 214000000 | J12: 270000000 | K12: 980 | L12: 0.42 | M12: =IFERROR(I12/H12,"") -> 2.9517241 | N12: =IFERROR(1/L12,"") -> 2.3809524 | O12: =IFERROR(J12/I12-1,"") -> 0.26168224 | P12: =IFERROR(H12/K12,"") -> 73979.592 | Q12: =I12*L12 -> 89880000 | R12: =Q12-H12 -> 17380000 | S12: =IFERROR(Q12/H12,"") -> 1.2397241 | T12: =IF(S12="","",IF(S12>=Asumsi!$B$16,"SEHAT",IF(S12>=1,"TIPIS","RUGI"))) -> TIPIS
A13: M7 | B13: 46293 | C13: 32000000 | D13: 14000000 | E13: 9000000 | F13: 20000000 | G13: 11000000 | H13: =SUM(C13:G13) -> 86000000 | I13: 270000000 | J13: 335000000 | K13: 1320 | L13: 0.42 | M13: =IFERROR(I13/H13,"") -> 3.1395349 | N13: =IFERROR(1/L13,"") -> 2.3809524 | O13: =IFERROR(J13/I13-1,"") -> 0.24074074 | P13: =IFERROR(H13/K13,"") -> 65151.515 | Q13: =I13*L13 -> 113400000 | R13: =Q13-H13 -> 27400000 | S13: =IFERROR(Q13/H13,"") -> 1.3186047 | T13: =IF(S13="","",IF(S13>=Asumsi!$B$16,"SEHAT",IF(S13>=1,"TIPIS","RUGI"))) -> SEHAT | U13: Gajian plus event tanggal kembar 10.10. Belanja naik, MER tetap sehat.
A14: M8 | B14: 46300 | C14: 24000000 | D14: 9000000 | E14: 5500000 | F14: 18000000 | G14: 6000000 | H14: =SUM(C14:G14) -> 62500000 | I14: 178000000 | J14: 215000000 | K14: 800 | L14: 0.42 | M14: =IFERROR(I14/H14,"") -> 2.848 | N14: =IFERROR(1/L14,"") -> 2.3809524 | O14: =IFERROR(J14/I14-1,"") -> 0.20786517 | P14: =IFERROR(H14/K14,"") -> 78125 | Q14: =I14*L14 -> 74760000 | R14: =Q14-H14 -> 12260000 | S14: =IFERROR(Q14/H14,"") -> 1.19616 | T14: =IF(S14="","",IF(S14>=Asumsi!$B$16,"SEHAT",IF(S14>=1,"TIPIS","RUGI"))) -> TIPIS | U14: Setelah event: permintaan turun, belanja dipangkas.
A15: TOTAL | C15: =SUM(C7:C14) -> 212500000 | D15: =SUM(D7:D14) -> 84000000 | E15: =SUM(E7:E14) -> 51000000 | F15: =SUM(F7:F14) -> 154500000 | G15: =SUM(G7:G14) -> 59000000 | H15: =SUM(H7:H14) -> 561000000 | I15: =SUM(I7:I14) -> 1643000000 | J15: =SUM(J7:J14) -> 1995000000 | K15: =SUM(K7:K14) -> 7665 | L15: =IFERROR(Q15/I15,"") -> 0.42 | M15: =IFERROR(I15/H15,"") -> 2.9286988 | N15: =IFERROR(1/L15,"") -> 2.3809524 | O15: =IFERROR(J15/I15-1,"") -> 0.21424224 | P15: =IFERROR(H15/K15,"") -> 73189.824 | Q15: =SUM(Q7:Q14) -> 690060000 | R15: =SUM(R7:R14) -> 129060000 | S15: =IFERROR(Q15/H15,"") -> 1.2300535
A17: Margin blended 42% adalah asumsi fiktif (input biru). MER di atas Break-even MER = bisnis untung di level kontribusi sebelum overhead. Klaim platform biasanya di atas aktual karena tiap platform mengambil kredit; minggu M4 sengaja dibuat terbalik.

Sheet Dashboard
A1: Dashboard Ringkasan
A2: Semua angka terhubung ke sheet platform. Ubah data di sheet platform, dashboard ikut berubah.
A5: Platform | B5: Biaya iklan (Rp) | C5: Nilai / omzet (Rp) | D5: ROAS | E5: Hasil utama | F5: Biaya per hasil (Rp) | G5: POAS | H5: Porsi biaya | I5: # SCALE | J5: # HOLD/FIX | K5: # CUT | L5: # LOW DATA
A6: Google Ads | B6: ='Google Ads'!F5 -> 114150000 | C6: ='Google Ads'!H5 -> 237450000 | D6: =IFERROR(C6/B6,"") -> 2.0801577 | E6: ='Google Ads'!G5 -> 1583 | F6: ='Google Ads'!M5 -> 72109.918 | G6: ='Google Ads'!P5 -> 0.97767411 | H6: =IFERROR(B6/$B$11,"") -> 0.38311797 | I6: =COUNTIF('Google Ads'!Q7:Q36,"SCALE") -> 2 | J6: =COUNTIF('Google Ads'!Q7:Q36,"HOLD")+COUNTIF('Google Ads'!Q7:Q36,"FIX*")+COUNTIF('Google Ads'!Q7:Q36,"CEK*") -> 3 | K6: =COUNTIF('Google Ads'!Q7:Q36,"CUT")+COUNTIF('Google Ads'!Q7:Q36,"FATIGUE") -> 1 | L6: =COUNTIF('Google Ads'!Q7:Q36,"LOW DATA") -> 0
A7: Meta Ads | B7: ='Meta Ads'!D5 -> 43200000 | C7: ='Meta Ads'!K5 -> 91800000 | D7: =IFERROR(C7/B7,"") -> 2.125 | E7: ='Meta Ads'!J5 -> 650 | F7: ='Meta Ads'!R5 -> 66461.538 | G7: ='Meta Ads'!T5 -> 0.99875 | H7: =IFERROR(B7/$B$11,"") -> 0.14499077 | I7: =COUNTIF('Meta Ads'!U7:U36,"SCALE") -> 1 | J7: =COUNTIF('Meta Ads'!U7:U36,"HOLD")+COUNTIF('Meta Ads'!U7:U36,"FIX*")+COUNTIF('Meta Ads'!U7:U36,"CEK*") -> 4 | K7: =COUNTIF('Meta Ads'!U7:U36,"CUT")+COUNTIF('Meta Ads'!U7:U36,"FATIGUE") -> 1 | L7: =COUNTIF('Meta Ads'!U7:U36,"LOW DATA") -> 1
A8: TikTok Ads | B8: ='TikTok Ads'!D5 -> 28600000 | C8: ='TikTok Ads'!J5 -> 86400000 | D8: =IFERROR(C8/B8,"") -> 3.020979 | E8: ='TikTok Ads'!I5 -> 576 | F8: ='TikTok Ads'!Q5 -> 49652.778 | G8: ='TikTok Ads'!S5 -> 1.4198601 | H8: =IFERROR(B8/$B$11,"") -> 0.09598926 | I8: =COUNTIF('TikTok Ads'!T7:T36,"SCALE") -> 3 | J8: =COUNTIF('TikTok Ads'!T7:T36,"HOLD")+COUNTIF('TikTok Ads'!T7:T36,"FIX*")+COUNTIF('TikTok Ads'!T7:T36,"CEK*") -> 2 | K8: =COUNTIF('TikTok Ads'!T7:T36,"CUT")+COUNTIF('TikTok Ads'!T7:T36,"FATIGUE") -> 1 | L8: =COUNTIF('TikTok Ads'!T7:T36,"LOW DATA") -> 1
A9: LinkedIn Ads | B9: ='LinkedIn Ads'!D5 -> 81000000 | C9: ='LinkedIn Ads'!K5 -> 260000000 | D9: =IFERROR(C9/B9,"") -> 3.2098765 | E9: ='LinkedIn Ads'!H5 -> 39 | F9: ='LinkedIn Ads'!P5 -> 2076923.1 | G9: ='LinkedIn Ads'!S5 -> 0.96296296 | H9: =IFERROR(B9/$B$11,"") -> 0.27185769 | I9: =COUNTIF('LinkedIn Ads'!T7:T36,"SCALE") -> 1 | J9: =COUNTIF('LinkedIn Ads'!T7:T36,"HOLD")+COUNTIF('LinkedIn Ads'!T7:T36,"FIX*")+COUNTIF('LinkedIn Ads'!T7:T36,"CEK*") -> 3 | K9: =COUNTIF('LinkedIn Ads'!T7:T36,"CUT")+COUNTIF('LinkedIn Ads'!T7:T36,"FATIGUE") -> 2 | L9: =COUNTIF('LinkedIn Ads'!T7:T36,"LOW DATA") -> 0
A10: Marketplace Ads | B10: =Marketplace!F5 -> 31000000 | C10: =Marketplace!G5 -> 109000000 | D10: =IFERROR(C10/B10,"") -> 3.516129 | E10: =Marketplace!D5 -> 470 | F10: =IFERROR(B10/E10,"") -> 65957.447 | G10: =Marketplace!U5 -> 1.2079194 | H10: =IFERROR(B10/$B$11,"") -> 0.1040443 | I10: =COUNTIF(Marketplace!Y7:Y36,"SCALE") -> 3 | J10: =COUNTIF(Marketplace!Y7:Y36,"HOLD")+COUNTIF(Marketplace!Y7:Y36,"FIX*")+COUNTIF(Marketplace!Y7:Y36,"CEK*") -> 5 | K10: =COUNTIF(Marketplace!Y7:Y36,"CUT")+COUNTIF(Marketplace!Y7:Y36,"FATIGUE") -> 1 | L10: =COUNTIF(Marketplace!Y7:Y36,"LOW DATA") -> 1
A11: TOTAL | B11: =SUM(B6:B10) -> 297950000 | C11: =SUM(C6:C10) -> 784650000 | D11: =IFERROR(C11/B11,"") -> 2.6334956 | G11: =IFERROR(SUMPRODUCT(B6:B10,G6:G10)/B11,"") -> 1.0431314 | H11: =SUM(H6:H10) -> 1 | I11: =SUM(I6:I10) -> 10 | J11: =SUM(J6:J10) -> 17 | K11: =SUM(K6:K10) -> 6 | L11: =SUM(L6:L10) -> 3
A12: Hasil utama per platform: Google konversi, Meta/TikTok pembelian, LinkedIn SQL, Marketplace pesanan. Nilai LinkedIn = omzet deal Won. Baris dengan hijau = tertaut ke sheet lain.
A14: KESEHATAN BISNIS (8 minggu, sheet Mingguan)
A15: MER 8 minggu | B15: =Mingguan!M15 -> 2.9286988
A16: Break-even MER | B16: =Mingguan!N15 -> 2.3809524
A17: POAS blended | B17: =Mingguan!S15 -> 1.2300535
A18: Laba setelah iklan (Rp) | B18: =Mingguan!R15 -> 129060000
A19: CAC blended (Rp) | B19: =Mingguan!P15 -> 73189.824
A20: Minggu MER terendah | B20: =INDEX(Mingguan!A7:A14,MATCH(MIN(Mingguan!M7:M14),Mingguan!M7:M14,0)) -> M4
A21: Minggu klaim platform terendah vs aktual | B21: =INDEX(Mingguan!A7:A14,MATCH(MIN(Mingguan!O7:O14),Mingguan!O7:O14,0)) -> M4
A23: BARIS PALING BERMASALAH (POAS terendah per platform)
A24: Platform | B24: Baris | C24: POAS
A25: Google Ads | B25: =INDEX('Google Ads'!A7:A36,MATCH(MIN('Google Ads'!P7:P36),'Google Ads'!P7:P36,0)) -> Search | Kompetitor | C25: =MIN('Google Ads'!P7:P36) -> 0.2437037
A26: Meta Ads | B26: =INDEX('Meta Ads'!A7:A36,MATCH(MIN('Meta Ads'!T7:T36),'Meta Ads'!T7:T36,0)) -> Founder Story | C26: =MIN('Meta Ads'!T7:T36) -> 0.2115
A27: TikTok Ads | B27: =INDEX('TikTok Ads'!A7:A36,MATCH(MIN('TikTok Ads'!S7:S36),'TikTok Ads'!S7:S36,0)) -> Unboxing Hemat v1 (tes baru) | C27: =MIN('TikTok Ads'!S7:S36) -> 0.3525
A28: Marketplace | B28: =INDEX(Marketplace!B7:B36,MATCH(MIN(Marketplace!U7:U36),Marketplace!U7:U36,0)) -> Kaos Polos 3 Pack | C28: =MIN(Marketplace!U7:U36) -> 0.24880952

Sheet Latihan
A1: Latihan dan Kunci Jawaban
A2: Kerjakan sendiri dulu, lalu bandingkan dengan kolom Kunci. Kunci = rumus hidup, ikut berubah jika datamu diganti. Salin prompt di kolom F ke agent (lampirkan file ini).
A4: No | B4: Level | C4: Sheet | D4: Tugas | E4: Kunci jawaban (rumus) | F4: Prompt siap salin
A5: 1 | B5: Pemula | C5: Asumsi | D5: Hitung break-even ROAS, target ROAS, dan target CPA untuk penjualan website. Apa arti POAS 1,0? | E5: ="Break-even ROAS "&TEXT(Asumsi!B12,"0.00")&"x, target ROAS "&TEXT(Asumsi!B17,"0.00")&"x, target CPA Rp "&TEXT(Asumsi!B15,"#,##0")&". POAS 1,0 = iklan impas di level kontribusi." -> Break-even ROAS 2.13x, target ROAS 2.77x, target CPA Rp 49,350. POAS 1,0 = iklan impas di level kontribusi. | F5: Pakai skill digital-ads-ultimate. Baca file Digital_Ads_Practice_Workbook_2026.xlsx yang kulampirkan. Dari sheet Asumsi, jelaskan break-even ROAS, target ROAS, target CPA, dan arti POAS 1,0 dengan bahasa sederhana.
A6: 2 | B6: Pemula | C6: Google Ads | D6: Campaign mana dengan POAS terendah? Bandingkan dengan campaign ROAS tertinggi: kenapa ROAS tinggi belum tentu sehat? | E6: ="Terendah: "&INDEX('Google Ads'!A7:A36,MATCH(MIN('Google Ads'!P7:P36),'Google Ads'!P7:P36,0))&" (POAS "&TEXT(MIN('Google Ads'!P7:P36),"0.00")&"). ROAS tertinggi: "&INDEX('Google Ads'!A7:A36,MATCH(MAX('Google Ads'!N7:N36),'Google Ads'!N7:N36,0))&" ("&TEXT(MAX('Google Ads'!N7:N36),"0.00")&"x), tapi itu brand search." -> Terendah: Search | Kompetitor (POAS 0.24). ROAS tertinggi: Search | Brand (6.61x), tapi itu brand search. | F6: Pakai skill digital-ads-ultimate. Baca file Digital_Ads_Practice_Workbook_2026.xlsx yang kulampirkan. Analisis sheet Google Ads. Urutkan campaign dari POAS terburuk, jelaskan kenapa Search Brand ROAS-nya tinggi tapi tidak boleh dijadikan bukti performa, dan beri rekomendasi P1/P2/P3.
A7: 3 | B7: Menengah | C7: Google Ads | D7: PMax terlihat ROAS 2,17. Berapa ROAS-nya jika porsi konversi brand dikeluarkan? Apa implikasinya untuk budget? | E7: ="ROAS PMax "&TEXT(INDEX('Google Ads'!N7:N36,MATCH("PMax | Feed Produk",'Google Ads'!A7:A36,0)),"0.00")&"x, tanpa brand "&TEXT(INDEX('Google Ads'!O7:O36,MATCH("PMax | Feed Produk",'Google Ads'!A7:A36,0)),"0.00")&"x. Pasang brand exclusion dan evaluasi dengan holdout." -> ROAS PMax 2.17x, tanpa brand 1.34x. Pasang brand exclusion dan evaluasi dengan holdout. | F7: Pakai skill digital-ads-ultimate. Baca file Digital_Ads_Practice_Workbook_2026.xlsx yang kulampirkan. Dari sheet Google Ads, hitung ROAS dan POAS PMax tanpa konversi brand. Apa yang harus saya ubah di pengaturan PMax dan bagaimana mengujinya?
A8: 4 | B8: Menengah | C8: Google Ads | D8: Berapa biaya yang bisa dihemat dengan menambah negative keyword dari tabel search terms? | E8: ="Rp "&TEXT(SUMIF('Google Ads'!H42:H55,"TAMBAH NEGATIF",'Google Ads'!D42:D55),"#,##0")&" per bulan dari "&COUNTIF('Google Ads'!H42:H55,"TAMBAH NEGATIF")&" search term." -> Rp 4,800,000 per bulan dari 3 search term. | F8: Pakai skill digital-ads-ultimate. Baca file Digital_Ads_Practice_Workbook_2026.xlsx yang kulampirkan. Dari tabel search terms di sheet Google Ads, buat daftar negative keyword (dan level penambahannya), term yang dipromosikan ke exact, dan estimasi penghematan.
A9: 5 | B9: Pemula | C9: Meta Ads | D9: Iklan mana yang kena FATIGUE dan apa tindakan yang tepat? | E9: =INDEX('Meta Ads'!A7:A36,MATCH("FATIGUE",'Meta Ads'!U7:U36,0))&": frekuensi "&TEXT(INDEX('Meta Ads'!M7:M36,MATCH("FATIGUE",'Meta Ads'!U7:U36,0)),"0.0")&". Matikan, ganti konsep baru, jangan hanya tukar warna." -> UGC Pain Hook v0 (lama): frekuensi 4.2. Matikan, ganti konsep baru, jangan hanya tukar warna. | F9: Pakai skill digital-ads-ultimate. Baca file Digital_Ads_Practice_Workbook_2026.xlsx yang kulampirkan. Dari sheet Meta Ads, identifikasi iklan yang fatigue berdasarkan frekuensi dan tren, lalu buat 3 konsep pengganti dengan hook berbeda.
A10: 6 | B10: Menengah | C10: Meta Ads | D10: Ada iklan dengan hook rate bagus tapi hampir tidak ada yang beli. Apa diagnosis dan 3 hal yang dicek? | E10: =INDEX('Meta Ads'!A7:A36,MATCH("FIX LANDING",'Meta Ads'!U7:U36,0))&": CVR "&TEXT(INDEX('Meta Ads'!Q7:Q36,MATCH("FIX LANDING",'Meta Ads'!U7:U36,0)),"0.0%")&". Cek pesan iklan vs halaman, kecepatan di browser Instagram, dan harga/penawaran." -> Founder Story: CVR 0.4%. Cek pesan iklan vs halaman, kecepatan di browser Instagram, dan harga/penawaran. | F10: Pakai skill digital-ads-ultimate. Baca file Digital_Ads_Practice_Workbook_2026.xlsx yang kulampirkan. Dari sheet Meta Ads, iklan Founder Story punya hook kuat tapi CVR rendah. Diagnosis per lapisan (perhatian, landing, konversi) dan beri langkah verifikasi.
A11: 7 | B11: Pemula | C11: TikTok Ads | D11: Kreatif mana yang FATIGUE dan mana yang hook-nya kuat tapi CTR rendah? | E11: ="Fatigue: "&INDEX('TikTok Ads'!A7:A36,MATCH("FATIGUE",'TikTok Ads'!T7:T36,0))&". CTA/body lemah: "&INDEX('TikTok Ads'!A7:A36,MATCH("FIX CTA/BODY",'TikTok Ads'!T7:T36,0))&"." -> Fatigue: Promo Flash Sale v3 (hari ke-18). CTA/body lemah: Trend Sound Dance. | F11: Pakai skill digital-ads-ultimate. Baca file Digital_Ads_Practice_Workbook_2026.xlsx yang kulampirkan. Dari sheet TikTok Ads, klasifikasikan tiap kreatif (scale, fix hook, fix CTA, fatigue) dan buat brief 3 konsep baru dari kreatif pemenang.
A12: 8 | B12: Menengah | C12: LinkedIn Ads | D12: Campaign lead gen punya biaya per lead termurah. Bandingkan biaya per lead dengan biaya per SQL. Apa pelajarannya? | E12: ="Biaya/lead Rp "&TEXT('LinkedIn Ads'!N7,"#,##0")&" (termurah) tapi biaya/SQL Rp "&TEXT('LinkedIn Ads'!P7,"#,##0")&" vs batas Rp "&TEXT(Asumsi!B36,"#,##0")&". Optimalkan ke SQL, bukan lead." -> Biaya/lead Rp 260,417 (termurah) tapi biaya/SQL Rp 3,125,000 vs batas Rp 1,620,000. Optimalkan ke SQL, bukan lead. | F12: Pakai skill digital-ads-ultimate. Baca file Digital_Ads_Practice_Workbook_2026.xlsx yang kulampirkan. Dari sheet LinkedIn Ads, urutkan campaign dari biaya per SQL, jelaskan kenapa Lead Gen Form murah tapi buruk, dan sarankan perbaikan kualifikasi dan umpan balik CRM.
A13: 9 | B13: Pemula | C13: Marketplace | D13: Produk mana ROAS tertingginya, dan berapa POAS-nya? Apa kesimpulan untuk target ROAS? | E13: =INDEX(Marketplace!B7:B36,MATCH(MAX(Marketplace!Q7:Q36),Marketplace!Q7:Q36,0))&": ROAS "&TEXT(MAX(Marketplace!Q7:Q36),"0.00")&"x, POAS "&TEXT(INDEX(Marketplace!U7:U36,MATCH(MAX(Marketplace!Q7:Q36),Marketplace!Q7:Q36,0)),"0.00")&", break-even ROAS "&TEXT(INDEX(Marketplace!T7:T36,MATCH(MAX(Marketplace!Q7:Q36),Marketplace!Q7:Q36,0)),"0.0")&"x. Target ROAS harus per produk." -> Kaos Polos 3 Pack: ROAS 5.00x, POAS 0.25, break-even ROAS 20.1x. Target ROAS harus per produk. | F13: Pakai skill digital-ads-ultimate. Baca file Digital_Ads_Practice_Workbook_2026.xlsx yang kulampirkan. Dari sheet Marketplace, hitung POAS dan break-even ROAS per produk. Beri verdict scale/hold/fix/cut dan target ROAS per produk untuk iklan GMV Max.
A14: 10 | B14: Menengah | C14: Marketplace | D14: Bandingkan TACoS dan POAS antar platform marketplace. Platform mana yang paling bergantung pada iklan? | E14: ="TACoS Shopee "&TEXT(Marketplace!E40,"0.0%")&", Tokopedia "&TEXT(Marketplace!E41,"0.0%")&", TikTok Shop "&TEXT(Marketplace!E42,"0.0%")&". POAS: "&TEXT(Marketplace!H40,"0.00")&" / "&TEXT(Marketplace!H41,"0.00")&" / "&TEXT(Marketplace!H42,"0.00")&"." -> TACoS Shopee 25.4%, Tokopedia 18.2%, TikTok Shop 23.7%. POAS: 1.11 / 1.16 / 1.39. | F14: Pakai skill digital-ads-ultimate. Baca file Digital_Ads_Practice_Workbook_2026.xlsx yang kulampirkan. Dari ringkasan per platform di sheet Marketplace, bandingkan TACoS dan POAS, lalu usulkan realokasi budget iklan antar marketplace dengan langkah bertahap.
A15: 11 | B15: Menengah | C15: Mingguan | D15: Minggu mana yang klaim platform lebih rendah dari omzet nyata? Apa penyebab paling mungkin dan kenapa MER tetap bisa dipercaya? | E15: ="Minggu "&INDEX(Mingguan!A7:A14,MATCH(MIN(Mingguan!O7:O14),Mingguan!O7:O14,0))&" (klaim "&TEXT(MIN(Mingguan!O7:O14),"0.0%")&" vs aktual). Penyebab: tracking rusak. MER memakai omzet bisnis, jadi tidak ikut rusak." -> Minggu M4 (klaim -2.6% vs aktual). Penyebab: tracking rusak. MER memakai omzet bisnis, jadi tidak ikut rusak. | F15: Pakai skill digital-ads-ultimate. Baca file Digital_Ads_Practice_Workbook_2026.xlsx yang kulampirkan. Dari sheet Mingguan, cari anomali antara klaim platform dan omzet bisnis, jelaskan penyebab, dan berikan checklist perbaikan tracking.
A16: 12 | B16: Lanjut | C16: Dashboard | D16: Platform mana yang POAS-nya terendah? Usulkan realokasi 10% budget dengan langkah, syarat, dan rollback. | E16: ="POAS terendah: "&INDEX(Dashboard!A6:A10,MATCH(MIN(Dashboard!G6:G10),Dashboard!G6:G10,0))&" ("&TEXT(MIN(Dashboard!G6:G10),"0.00")&"). Pastikan alasannya (peran Create, siklus B2B) sebelum memotong." -> POAS terendah: LinkedIn Ads (0.96). Pastikan alasannya (peran Create, siklus B2B) sebelum memotong. | F16: Pakai skill digital-ads-ultimate. Baca file Digital_Ads_Practice_Workbook_2026.xlsx yang kulampirkan. Dari sheet Dashboard dan semua sheet platform, buat rekomendasi realokasi 10% budget antar platform dengan format P1/P2/P3 lengkap bukti, dampak, confidence, verifikasi, dan rollback.
A17: 13 | B17: Lanjut | C17: Semua | D17: Tulis laporan mingguan lengkap: scorecard, yang berhasil, yang gagal, diagnosis per lapisan, 5 rekomendasi berurutan, tes minggu depan. | E17: Jawaban terbuka. Cek: tiap rekomendasi punya bukti angka, dampak, confidence, cara verifikasi, rollback. | F17: Pakai skill digital-ads-ultimate. Baca file Digital_Ads_Practice_Workbook_2026.xlsx yang kulampirkan. Tulis laporan mingguan untuk brand Nusa Apparel dari seluruh sheet. Gunakan MER, POAS, dan TACoS, bukan hanya ROAS. Sertakan rekomendasi P1/P2/P3.
A18: 14 | B18: Lanjut | C18: Semua | D18: Ganti data dengan data akunmu sendiri (sel biru), ubah Asumsi, lalu minta agent audit seluruh akun. | E18: Jawaban terbuka. Cek: Asumsi sudah diganti, tidak ada sel biru berisi data contoh, verdict masuk akal. | F18: Pakai skill digital-ads-ultimate. Ini workbook dengan data akun saya (brand [BRAND]). Audit semua platform, tandai data yang kurang, dan beri rencana 30/60/90 hari.
